{"data":{"observation":{"a":368.14404296875,"s":164.947265625,"ld":180.0,"qdel":0.0},"cca_rate":null,"belief_bounds":{"min_c":11.623046875,"max_c":30.3837890625,"min_b":10.0,"max_b":25.2001953125,"min_if":23.19677734375,"max_if":23.19677734375},"metrics":{"loss":85.0,"neg_delivered":-62.76171875,"qdel":0.0,"shrink_c":false,"shrink_b":false,"shrink_maxc_mul":false,"shrink_maxc_add":false,"shrink_minc_mul":false,"shrink_minc_add":false},"chosen_move":{"CCA":{"rate":5.8115234375}},"chosen_value":{"Value":{"belief_bounds":{"min_c":7.630859375,"max_c":11.568359375,"min_b":11.634765625,"max_b":15.443359375,"min_if":15.21728515625,"max_if":18.41455078125},"metrics":{"loss":88.544921875,"neg_delivered":-80.412109375,"qdel":1.0,"shrink_c":true,"shrink_b":true,"shrink_maxc_mul":true,"shrink_maxc_add":true,"shrink_minc_mul":false,"shrink_minc_add":false}}}},"children":[{"data":{"observation":{"a":368.14404296875,"s":164.947265625,"ld":180.0,"qdel":0.0},"cca_rate":5.8115234375,"belief_bounds":{"min_c":11.623046875,"max_c":30.3837890625,"min_b":10.0,"max_b":25.2001953125,"min_if":23.19677734375,"max_if":23.19677734375},"metrics":{"loss":85.0,"neg_delivered":-62.76171875,"qdel":0.0,"shrink_c":false,"shrink_b":false,"shrink_maxc_mul":false,"shrink_maxc_add":false,"shrink_minc_mul":false,"shrink_minc_add":false},"chosen_move":{"Network":{"ld":180.0,"s":170.99609375,"qdel":1.0}},"chosen_value":{"Value":{"belief_bounds":{"min_c":7.630859375,"max_c":11.568359375,"min_b":11.634765625,"max_b":15.443359375,"min_if":15.21728515625,"max_if":18.41455078125},"metrics":{"loss":88.544921875,"neg_delivered":-80.412109375,"qdel":1.0,"shrink_c":true,"shrink_b":true,"shrink_maxc_mul":true,"shrink_maxc_add":true,"shrink_minc_mul":false,"shrink_minc_add":false}}}},"children":[{"data":{"observation":{"a":373.95556640625,"s":193.923828125,"ld":180.0,"qdel":0.0},"cca_rate":null,"belief_bounds":{"min_c":14.5068359375,"max_c":120.0,"min_b":0.03125,"max_b":120.0,"min_if":0.03173828125,"max_if":0.03173828125},"metrics":{"loss":84.0,"neg_delivered":-91.73828125,"qdel":0.0,"shrink_c":false,"shrink_b":false,"shrink_maxc_mul":false,"shrink_maxc_add":false,"shrink_minc_mul":false,"shrink_minc_add":true},"chosen_move":{"CCA":{"rate":120.0}},"chosen_value":{"Value":{"belief_bounds":{"min_c":14.4990234375,"max_c":16.404296875,"min_b":8.71484375,"max_b":120.0,"min_if":23.21044921875,"max_if":120.03173828125},"metrics":{"loss":83.0,"neg_delivered":-91.73828125,"qdel":0.0,"shrink_c":true,"shrink_b":false,"shrink_maxc_mul":false,"shrink_maxc_add":true,"shrink_minc_mul":false,"shrink_minc_add":true}}}},"children":[{"data":{"observation":{"a":373.95556640625,"s":193.923828125,"ld":180.0,"qdel":0.0},"cca_rate":7.25341796875,"belief_bounds":{"min_c":14.5068359375,"max_c":120.0,"min_b":0.03125,"max_b":120.0,"min_if":0.03173828125,"max_if":0.03173828125},"metrics":{"loss":84.0,"neg_delivered":-91.73828125,"qdel":0.0,"shrink_c":false,"shrink_b":false,"shrink_maxc_mul":false,"shrink_maxc_add":false,"shrink_minc_mul":false,"shrink_minc_add":true},"chosen_move":{"Network":{"ld":180.0,"s":201.18359375,"qdel":0.0}},"chosen_value":{"Value":{"belief_bounds":{"min_c":14.5078125,"max_c":120.0,"min_b":0.025390625,"max_b":120.0,"min_if":0.025390625,"max_if":0.025390625},"metrics":{"loss":83.0,"neg_delivered":-98.998046875,"qdel":0.0,"shrink_c":false,"shrink_b":false,"shrink_maxc_mul":false,"shrink_maxc_add":false,"shrink_minc_mul":false,"shrink_minc_add":true}}}},"children":[{"data":{"observation":{"a":381.208984375,"s":201.18359375,"ld":180.0,"qdel":0.0},"cca_rate":null,"belief_bounds":{"min_c":14.5078125,"max_c":120.0,"min_b":0.025390625,"max_b":120.0,"min_if":0.025390625,"max_if":0.025390625},"metrics":{"loss":83.0,"neg_delivered":-98.998046875,"qdel":0.0,"shrink_c":false,"shrink_b":false,"shrink_maxc_mul":false,"shrink_maxc_add":false,"shrink_minc_mul":false,"shrink_minc_add":true},"chosen_move":null,"chosen_value":null},"children":[]},{"data":{"observation":{"a":381.208984375,"s":193.923828125,"ld":180.0,"qdel":0.0},"cca_rate":null,"belief_bounds":{"min_c":14.4990234375,"max_c":16.404296875,"min_b":8.7119140625,"max_b":120.0,"min_if":7.28515625,"max_if":7.28515625},"metrics":{"loss":83.0,"neg_delivered":-91.73828125,"qdel":0.0,"shrink_c":true,"shrink_b":false,"shrink_maxc_mul":false,"shrink_maxc_add":true,"shrink_minc_mul":false,"shrink_minc_add":true},"chosen_move":null,"chosen_value":null},"children":[]}]},{"data":{"observation":{"a":373.95556640625,"s":193.923828125,"ld":180.0,"qdel":0.0},"cca_rate":120.0,"belief_bounds":{"min_c":14.5068359375,"max_c":120.0,"min_b":0.03125,"max_b":120.0,"min_if":0.03173828125,"max_if":0.03173828125},"metrics":{"loss":84.0,"neg_delivered":-91.73828125,"qdel":0.0,"shrink_c":false,"shrink_b":false,"shrink_maxc_mul":false,"shrink_maxc_add":false,"shrink_minc_mul":false,"shrink_minc_add":true},"chosen_move":{"Network":{"ld":180.0,"s":193.923828125,"qdel":0.0}},"chosen_value":{"Value":{"belief_bounds":{"min_c":14.4990234375,"max_c":16.404296875,"min_b":8.71484375,"max_b":120.0,"min_if":23.21044921875,"max_if":120.03173828125},"metrics":{"loss":83.0,"neg_delivered":-91.73828125,"qdel":0.0,"shrink_c":true,"shrink_b":false,"shrink_maxc_mul":false,"shrink_maxc_add":true,"shrink_minc_mul":false,"shrink_minc_add":true}}}},"children":[{"data":{"observation":{"a":493.95556640625,"s":313.94140625,"ld":180.0,"qdel":0.0},"cca_rate":null,"belief_bounds":{"min_c":119.986328125,"max_c":120.0,"min_b":0.013671875,"max_b":120.0,"min_if":0.01416015625,"max_if":0.01416015625},"metrics":{"loss":83.0,"neg_delivered":-211.755859375,"qdel":0.0,"shrink_c":true,"shrink_b":false,"shrink_maxc_mul":false,"shrink_maxc_add":false,"shrink_minc_mul":true,"shrink_minc_add":true},"chosen_move":null,"chosen_value":null},"children":[]},{"data":{"observation":{"a":493.95556640625,"s":193.923828125,"ld":180.0,"qdel":0.0},"cca_rate":null,"belief_bounds":{"min_c":14.4990234375,"max_c":16.404296875,"min_b":8.71484375,"max_b":120.0,"min_if":23.21044921875,"max_if":120.03173828125},"metrics":{"loss":83.0,"neg_delivered":-91.73828125,"qdel":0.0,"shrink_c":true,"shrink_b":false,"shrink_maxc_mul":false,"shrink_maxc_add":true,"shrink_minc_mul":false,"shrink_minc_add":true},"chosen_move":null,"chosen_value":null},"children":[]}]},{"data":{"observation":{"a":373.95556640625,"s":193.923828125,"ld":180.0,"qdel":0.0},"cca_rate":15.5068359375,"belief_bounds":{"min_c":14.5068359375,"max_c":120.0,"min_b":0.03125,"max_b":120.0,"min_if":0.03173828125,"max_if":0.03173828125},"metrics":{"loss":84.0,"neg_delivered":-91.73828125,"qdel":0.0,"shrink_c":false,"shrink_b":false,"shrink_maxc_mul":false,"shrink_maxc_add":false,"shrink_minc_mul":false,"shrink_minc_add":true},"chosen_move":{"Network":{"ld":180.0,"s":209.4462890625,"qdel":0.0}},"chosen_value":{"Value":{"belief_bounds":{"min_c":15.4912109375,"max_c":120.0,"min_b":0.037109375,"max_b":120.0,"min_if":0.01611328125,"max_if":0.01611328125},"metrics":{"loss":83.0,"neg_delivered":-107.2607421875,"qdel":0.0,"shrink_c":false,"shrink_b":false,"shrink_maxc_mul":false,"shrink_maxc_add":false,"shrink_minc_mul":false,"shrink_minc_add":true}}}},"children":[{"data":{"observation":{"a":389.46240234375,"s":209.4462890625,"ld":180.0,"qdel":0.0},"cca_rate":null,"belief_bounds":{"min_c":15.4912109375,"max_c":120.0,"min_b":0.037109375,"max_b":120.0,"min_if":0.01611328125,"max_if":0.01611328125},"metrics":{"loss":83.0,"neg_delivered":-107.2607421875,"qdel":0.0,"shrink_c":false,"shrink_b":false,"shrink_maxc_mul":false,"shrink_maxc_add":false,"shrink_minc_mul":false,"shrink_minc_add":true},"chosen_move":null,"chosen_value":null},"children":[]}]},{"data":{"observation":{"a":373.95556640625,"s":193.923828125,"ld":180.0,"qdel":0.0},"cca_rate":29.013671875,"belief_bounds":{"min_c":14.5068359375,"max_c":120.0,"min_b":0.03125,"max_b":120.0,"min_if":0.03173828125,"max_if":0.03173828125},"metrics":{"loss":84.0,"neg_delivered":-91.73828125,"qdel":0.0,"shrink_c":false,"shrink_b":false,"shrink_maxc_mul":false,"shrink_maxc_add":false,"shrink_minc_mul":false,"shrink_minc_add":true},"chosen_move":{"Network":{"ld":180.0,"s":222.9365234375,"qdel":0.0}},"chosen_value":{"Value":{"belief_bounds":{"min_c":28.9814453125,"max_c":120.0,"min_b":0.0322265625,"max_b":120.0,"min_if":0.03271484375,"max_if":0.03271484375},"metrics":{"loss":83.0,"neg_delivered":-120.7509765625,"qdel":0.0,"shrink_c":false,"shrink_b":false,"shrink_maxc_mul":false,"shrink_maxc_add":false,"shrink_minc_mul":true,"shrink_minc_add":true}}}},"children":[{"data":{"observation":{"a":402.96923828125,"s":222.9365234375,"ld":180.0,"qdel":0.0},"cca_rate":null,"belief_bounds":{"min_c":28.9814453125,"max_c":120.0,"min_b":0.0322265625,"max_b":120.0,"min_if":0.03271484375,"max_if":0.03271484375},"metrics":{"loss":83.0,"neg_delivered":-120.7509765625,"qdel":0.0,"shrink_c":false,"shrink_b":false,"shrink_maxc_mul":false,"shrink_maxc_add":false,"shrink_minc_mul":true,"shrink_minc_add":true},"chosen_move":null,"chosen_value":null},"children":[]}]},{"data":{"observation":{"a":373.95556640625,"s":193.923828125,"ld":180.0,"qdel":0.0},"cca_rate":14.5068359375,"belief_bounds":{"min_c":14.5068359375,"max_c":120.0,"min_b":0.03125,"max_b":120.0,"min_if":0.03173828125,"max_if":0.03173828125},"metrics":{"loss":84.0,"neg_delivered":-91.73828125,"qdel":0.0,"shrink_c":false,"shrink_b":false,"shrink_maxc_mul":false,"shrink_maxc_add":false,"shrink_minc_mul":false,"shrink_minc_add":true},"chosen_move":{"Network":{"ld":180.0,"s":208.451171875,"qdel":0.0}},"chosen_value":{"Value":{"belief_bounds":{"min_c":14.5048828125,"max_c":120.0,"min_b":0.0107421875,"max_b":120.0,"min_if":0.01123046875,"max_if":0.01123046875},"metrics":{"loss":83.0,"neg_delivered":-106.265625,"qdel":0.0,"shrink_c":false,"shrink_b":false,"shrink_maxc_mul":false,"shrink_maxc_add":false,"shrink_minc_mul":false,"shrink_minc_add":true}}}},"children":[{"data":{"observation":{"a":388.46240234375,"s":208.451171875,"ld":180.0,"qdel":0.0},"cca_rate":null,"belief_bounds":{"min_c":14.5048828125,"max_c":120.0,"min_b":0.0107421875,"max_b":120.0,"min_if":0.01123046875,"max_if":0.01123046875},"metrics":{"loss":83.0,"neg_delivered":-106.265625,"qdel":0.0,"shrink_c":false,"shrink_b":false,"shrink_maxc_mul":false,"shrink_maxc_add":false,"shrink_minc_mul":false,"shrink_minc_add":true},"chosen_move":null,"chosen_value":null},"children":[]}]}]},{"data":{"observation":{"a":373.95556640625,"s":170.99609375,"ld":180.0,"qdel":1.0},"cca_rate":null,"belief_bounds":{"min_c":11.6015625,"max_c":11.6015625,"min_b":11.6015625,"max_b":120.0,"min_if":17.39990234375,"max_if":22.95947265625},"metrics":{"loss":84.0,"neg_delivered":-68.810546875,"qdel":0.0,"shrink_c":true,"shrink_b":false,"shrink_maxc_mul":true,"shrink_maxc_add":true,"shrink_minc_mul":false,"shrink_minc_add":false},"chosen_move":{"CCA":{"rate":12.6015625}},"chosen_value":{"Value":{"belief_bounds":{"min_c":7.630859375,"max_c":11.568359375,"min_b":11.634765625,"max_b":15.443359375,"min_if":15.21728515625,"max_if":18.41455078125},"metrics":{"loss":88.544921875,"neg_delivered":-80.412109375,"qdel":1.0,"shrink_c":true,"shrink_b":true,"shrink_maxc_mul":true,"shrink_maxc_add":true,"shrink_minc_mul":false,"shrink_minc_add":false}}}},"children":[{"data":{"observation":{"a":373.95556640625,"s":170.99609375,"ld":180.0,"qdel":1.0},"cca_rate":5.80078125,"belief_bounds":{"min_c":11.6015625,"max_c":11.6015625,"min_b":11.6015625,"max_b":120.0,"min_if":17.39990234375,"max_if":22.95947265625},"metrics":{"loss":84.0,"neg_delivered":-68.810546875,"qdel":0.0,"shrink_c":true,"shrink_b":false,"shrink_maxc_mul":true,"shrink_maxc_add":true,"shrink_minc_mul":false,"shrink_minc_add":false},"chosen_move":{"Network":{"ld":185.580078125,"s":182.5849609375,"qdel":1.0}},"chosen_value":{"Value":{"belief_bounds":{"min_c":7.6455078125,"max_c":11.5595703125,"min_b":10.6083984375,"max_b":15.421875,"min_if":10.62646484375,"max_if":11.59130859375},"metrics":{"loss":88.580078125,"neg_delivered":-80.3994140625,"qdel":0.0,"shrink_c":true,"shrink_b":true,"shrink_maxc_mul":true,"shrink_maxc_add":true,"shrink_minc_mul":false,"shrink_minc_add":false}}}},"children":[{"data":{"observation":{"a":379.75634765625,"s":194.16796875,"ld":185.580078125,"qdel":0.0},"cca_rate":null,"belief_bounds":{"min_c":11.58984375,"max_c":11.58984375,"min_b":11.5751953125,"max_b":11.5751953125,"min_if":0.00830078125,"max_if":0.00830078125},"metrics":{"loss":88.580078125,"neg_delivered":-91.982421875,"qdel":0.0,"shrink_c":true,"shrink_b":true,"shrink_maxc_mul":true,"shrink_maxc_add":true,"shrink_minc_mul":false,"shrink_minc_add":false},"chosen_move":null,"chosen_value":null},"children":[]},{"data":{"observation":{"a":379.75634765625,"s":194.16796875,"ld":180.0,"qdel":0.0},"cca_rate":null,"belief_bounds":{"min_c":11.6015625,"max_c":11.6015625,"min_b":17.1484375,"max_b":120.0,"min_if":5.58837890625,"max_if":5.58837890625},"metrics":{"loss":83.0,"neg_delivered":-91.982421875,"qdel":0.0,"shrink_c":true,"shrink_b":false,"shrink_maxc_mul":true,"shrink_maxc_add":true,"shrink_minc_mul":false,"shrink_minc_add":false},"chosen_move":null,"chosen_value":null},"children":[]},{"data":{"observation":{"a":379.75634765625,"s":182.5849609375,"ld":185.580078125,"qdel":1.0},"cca_rate":null,"belief_bounds":{"min_c":7.6455078125,"max_c":11.5595703125,"min_b":10.6083984375,"max_b":15.421875,"min_if":10.62646484375,"max_if":11.59130859375},"metrics":{"loss":88.580078125,"neg_delivered":-80.3994140625,"qdel":0.0,"shrink_c":true,"shrink_b":true,"shrink_maxc_mul":true,"shrink_maxc_add":true,"shrink_minc_mul":false,"shrink_minc_add":false},"chosen_move":null,"chosen_value":null},"children":[]},{"data":{"observation":{"a":379.75634765625,"s":182.5849609375,"ld":180.0,"qdel":2.0},"cca_rate":null,"belief_bounds":{"min_c":7.623046875,"max_c":11.5595703125,"min_b":11.6181640625,"max_b":120.0,"min_if":11.63916015625,"max_if":17.17138671875},"metrics":{"loss":83.0,"neg_delivered":-80.3994140625,"qdel":1.0,"shrink_c":true,"shrink_b":false,"shrink_maxc_mul":true,"shrink_maxc_add":true,"shrink_minc_mul":false,"shrink_minc_add":false},"chosen_move":null,"chosen_value":null},"children":[]},{"data":{"observation":{"a":379.75634765625,"s":182.5849609375,"ld":180.0,"qdel":1.0},"cca_rate":null,"belief_bounds":{"min_c":7.6083984375,"max_c":11.5654296875,"min_b":10.6044921875,"max_b":15.41796875,"min_if":10.62255859375,"max_if":11.57080078125},"metrics":{"loss":83.0,"neg_delivered":-80.3994140625,"qdel":0.0,"shrink_c":true,"shrink_b":true,"shrink_maxc_mul":true,"shrink_maxc_add":true,"shrink_minc_mul":false,"shrink_minc_add":false},"chosen_move":null,"chosen_value":null},"children":[]}]},{"data":{"observation":{"a":373.95556640625,"s":170.99609375,"ld":180.0,"qdel":1.0},"cca_rate":12.6015625,"belief_bounds":{"min_c":11.6015625,"max_c":11.6015625,"min_b":11.6015625,"max_b":120.0,"min_if":17.39990234375,"max_if":22.95947265625},"metrics":{"loss":84.0,"neg_delivered":-68.810546875,"qdel":0.0,"shrink_c":true,"shrink_b":false,"shrink_maxc_mul":true,"shrink_maxc_add":true,"shrink_minc_mul":false,"shrink_minc_add":false},"chosen_move":{"Network":{"ld":185.544921875,"s":182.59765625,"qdel":2.0}},"chosen_value":{"Value":{"belief_bounds":{"min_c":7.630859375,"max_c":11.568359375,"min_b":11.634765625,"max_b":15.443359375,"min_if":15.21728515625,"max_if":18.41455078125},"metrics":{"loss":88.544921875,"neg_delivered":-80.412109375,"qdel":1.0,"shrink_c":true,"shrink_b":true,"shrink_maxc_mul":true,"shrink_maxc_add":true,"shrink_minc_mul":false,"shrink_minc_add":false}}}},"children":[{"data":{"observation":{"a":386.55712890625,"s":194.19921875,"ld":185.5146484375,"qdel":0.0},"cca_rate":null,"belief_bounds":{"min_c":11.6015625,"max_c":11.6015625,"min_b":11.63330078125,"max_b":11.63330078125,"min_if":6.84326171875,"max_if":6.84326171875},"metrics":{"loss":88.5146484375,"neg_delivered":-92.013671875,"qdel":0.0,"shrink_c":true,"shrink_b":true,"shrink_maxc_mul":true,"shrink_maxc_add":true,"shrink_minc_mul":false,"shrink_minc_add":false},"chosen_move":null,"chosen_value":null},"children":[]},{"data":{"observation":{"a":386.55712890625,"s":194.19921875,"ld":180.0,"qdel":0.0},"cca_rate":null,"belief_bounds":{"min_c":11.6015625,"max_c":11.6015625,"min_b":17.1484375,"max_b":120.0,"min_if":12.35791015625,"max_if":12.35791015625},"metrics":{"loss":83.0,"neg_delivered":-92.013671875,"qdel":0.0,"shrink_c":true,"shrink_b":false,"shrink_maxc_mul":true,"shrink_maxc_add":true,"shrink_minc_mul":false,"shrink_minc_add":false},"chosen_move":null,"chosen_value":null},"children":[]},{"data":{"observation":{"a":386.55712890625,"s":182.59765625,"ld":185.544921875,"qdel":2.0},"cca_rate":null,"belief_bounds":{"min_c":7.630859375,"max_c":11.568359375,"min_b":11.634765625,"max_b":15.443359375,"min_if":15.21728515625,"max_if":18.41455078125},"metrics":{"loss":88.544921875,"neg_delivered":-80.412109375,"qdel":1.0,"shrink_c":true,"shrink_b":true,"shrink_maxc_mul":true,"shrink_maxc_add":true,"shrink_minc_mul":false,"shrink_minc_add":false},"chosen_move":null,"chosen_value":null},"children":[]},{"data":{"observation":{"a":386.55712890625,"s":182.59765625,"ld":185.544921875,"qdel":1.0},"cca_rate":null,"belief_bounds":{"min_c":7.595703125,"max_c":11.6005859375,"min_b":10.623046875,"max_b":15.4599609375,"min_if":14.19384765625,"max_if":18.36865234375},"metrics":{"loss":88.544921875,"neg_delivered":-80.412109375,"qdel":0.0,"shrink_c":true,"shrink_b":true,"shrink_maxc_mul":true,"shrink_maxc_add":true,"shrink_minc_mul":false,"shrink_minc_add":false},"chosen_move":null,"chosen_value":null},"children":[]},{"data":{"observation":{"a":386.55712890625,"s":182.59765625,"ld":180.0,"qdel":2.0},"cca_rate":null,"belief_bounds":{"min_c":7.61328125,"max_c":11.6015625,"min_b":11.6259765625,"max_b":120.0,"min_if":15.20947265625,"max_if":23.95947265625},"metrics":{"loss":83.0,"neg_delivered":-80.412109375,"qdel":1.0,"shrink_c":true,"shrink_b":false,"shrink_maxc_mul":true,"shrink_maxc_add":true,"shrink_minc_mul":false,"shrink_minc_add":false},"chosen_move":null,"chosen_value":null},"children":[]},{"data":{"observation":{"a":386.55712890625,"s":182.59765625,"ld":180.0,"qdel":1.0},"cca_rate":null,"belief_bounds":{"min_c":7.61328125,"max_c":11.5703125,"min_b":10.6103515625,"max_b":15.4375,"min_if":14.23193359375,"max_if":18.40185546875},"metrics":{"loss":83.0,"neg_delivered":-80.412109375,"qdel":0.0,"shrink_c":true,"shrink_b":true,"shrink_maxc_mul":true,"shrink_maxc_add":true,"shrink_minc_mul":false,"shrink_minc_add":false},"chosen_move":null,"chosen_value":null},"children":[]}]},{"data":{"observation":{"a":373.95556640625,"s":170.99609375,"ld":180.0,"qdel":1.0},"cca_rate":23.203125,"belief_bounds":{"min_c":11.6015625,"max_c":11.6015625,"min_b":11.6015625,"max_b":120.0,"min_if":17.39990234375,"max_if":22.95947265625},"metrics":{"loss":84.0,"neg_delivered":-68.810546875,"qdel":0.0,"shrink_c":true,"shrink_b":false,"shrink_maxc_mul":true,"shrink_maxc_add":true,"shrink_minc_mul":false,"shrink_minc_add":false},"chosen_move":{"Network":{"ld":191.396484375,"s":194.16796875,"qdel":0.0}},"chosen_value":{"Value":{"belief_bounds":{"min_c":11.6015625,"max_c":11.6015625,"min_b":5.78125,"max_b":11.5625,"min_if":5.78173828125,"max_if":11.59423828125},"metrics":{"loss":94.396484375,"neg_delivered":-91.982421875,"qdel":0.0,"shrink_c":true,"shrink_b":true,"shrink_maxc_mul":true,"shrink_maxc_add":true,"shrink_minc_mul":false,"shrink_minc_add":false}}}},"children":[{"data":{"observation":{"a":397.15869140625,"s":194.16796875,"ld":191.396484375,"qdel":0.0},"cca_rate":null,"belief_bounds":{"min_c":11.6015625,"max_c":11.6015625,"min_b":5.78125,"max_b":11.5625,"min_if":5.78173828125,"max_if":11.59423828125},"metrics":{"loss":94.396484375,"neg_delivered":-91.982421875,"qdel":0.0,"shrink_c":true,"shrink_b":true,"shrink_maxc_mul":true,"shrink_maxc_add":true,"shrink_minc_mul":false,"shrink_minc_add":false},"chosen_move":null,"chosen_value":null},"children":[]}]},{"data":{"observation":{"a":373.95556640625,"s":170.99609375,"ld":180.0,"qdel":1.0},"cca_rate":11.6015625,"belief_bounds":{"min_c":11.6015625,"max_c":11.6015625,"min_b":11.6015625,"max_b":120.0,"min_if":17.39990234375,"max_if":22.95947265625},"metrics":{"loss":84.0,"neg_delivered":-68.810546875,"qdel":0.0,"shrink_c":true,"shrink_b":false,"shrink_maxc_mul":true,"shrink_maxc_add":true,"shrink_minc_mul":false,"shrink_minc_add":false},"chosen_move":{"Network":{"ld":185.55078125,"s":194.1669921875,"qdel":0.0}},"chosen_value":{"Value":{"belief_bounds":{"min_c":11.5859375,"max_c":11.5859375,"min_b":11.59765625,"max_b":11.59765625,"min_if":5.83935546875,"max_if":5.83935546875},"metrics":{"loss":88.55078125,"neg_delivered":-91.9814453125,"qdel":0.0,"shrink_c":true,"shrink_b":true,"shrink_maxc_mul":true,"shrink_maxc_add":true,"shrink_minc_mul":false,"shrink_minc_add":false}}}},"children":[{"data":{"observation":{"a":385.55712890625,"s":194.1669921875,"ld":185.55078125,"qdel":0.0},"cca_rate":null,"belief_bounds":{"min_c":11.5859375,"max_c":11.5859375,"min_b":11.59765625,"max_b":11.59765625,"min_if":5.83935546875,"max_if":5.83935546875},"metrics":{"loss":88.55078125,"neg_delivered":-91.9814453125,"qdel":0.0,"shrink_c":true,"shrink_b":true,"shrink_maxc_mul":true,"shrink_maxc_add":true,"shrink_minc_mul":false,"shrink_minc_add":false},"chosen_move":null,"chosen_value":null},"children":[]}]}]}]},{"data":{"observation":{"a":368.14404296875,"s":164.947265625,"ld":180.0,"qdel":0.0},"cca_rate":30.3837890625,"belief_bounds":{"min_c":11.623046875,"max_c":30.3837890625,"min_b":10.0,"max_b":25.2001953125,"min_if":23.19677734375,"max_if":23.19677734375},"metrics":{"loss":85.0,"neg_delivered":-62.76171875,"qdel":0.0,"shrink_c":false,"shrink_b":false,"shrink_maxc_mul":false,"shrink_maxc_add":false,"shrink_minc_mul":false,"shrink_minc_add":false},"chosen_move":{"Network":{"ld":180.0,"s":170.99609375,"qdel":1.0}},"chosen_value":{"Value":{"belief_bounds":{"min_c":11.5751953125,"max_c":11.5751953125,"min_b":11.5859375,"max_b":11.6318359375,"min_if":11.58935546875,"max_if":11.63427734375},"metrics":{"loss":107.32421875,"neg_delivered":-91.9599609375,"qdel":0.0,"shrink_c":true,"shrink_b":true,"shrink_maxc_mul":true,"shrink_maxc_add":true,"shrink_minc_mul":false,"shrink_minc_add":false}}}},"children":[{"data":{"observation":{"a":398.52783203125,"s":218.4853515625,"ld":180.0,"qdel":0.0},"cca_rate":null,"belief_bounds":{"min_c":30.341796875,"max_c":120.0,"min_b":0.0419921875,"max_b":120.0,"min_if":0.04248046875,"max_if":0.04248046875},"metrics":{"loss":84.0,"neg_delivered":-116.2998046875,"qdel":0.0,"shrink_c":false,"shrink_b":false,"shrink_maxc_mul":false,"shrink_maxc_add":false,"shrink_minc_mul":true,"shrink_minc_add":true},"chosen_move":{"CCA":{"rate":120.0}},"chosen_value":{"Value":{"belief_bounds":{"min_c":30.34130859375,"max_c":30.34130859375,"min_b":0.0009765625,"max_b":0.0009765625,"min_if":30.34228515625,"max_if":30.34228515625},"metrics":{"loss":83.041015625,"neg_delivered":-116.2998046875,"qdel":0.0,"shrink_c":true,"shrink_b":true,"shrink_maxc_mul":false,"shrink_maxc_add":false,"shrink_minc_mul":true,"shrink_minc_add":true}}}},"children":[{"data":{"observation":{"a":398.52783203125,"s":218.4853515625,"ld":180.0,"qdel":0.0},"cca_rate":15.1708984375,"belief_bounds":{"min_c":30.341796875,"max_c":120.0,"min_b":0.0419921875,"max_b":120.0,"min_if":0.04248046875,"max_if":0.04248046875},"metrics":{"loss":84.0,"neg_delivered":-116.2998046875,"qdel":0.0,"shrink_c":false,"shrink_b":false,"shrink_maxc_mul":false,"shrink_maxc_add":false,"shrink_minc_mul":true,"shrink_minc_add":true},"chosen_move":{"Network":{"ld":180.0,"s":233.669921875,"qdel":0.0}},"chosen_value":{"Value":{"belief_bounds":{"min_c":30.341796875,"max_c":120.0,"min_b":0.0283203125,"max_b":120.0,"min_if":0.02880859375,"max_if":0.02880859375},"metrics":{"loss":83.0,"neg_delivered":-131.484375,"qdel":0.0,"shrink_c":false,"shrink_b":false,"shrink_maxc_mul":false,"shrink_maxc_add":false,"shrink_minc_mul":true,"shrink_minc_add":true}}}},"children":[{"data":{"observation":{"a":413.69873046875,"s":233.669921875,"ld":180.009765625,"qdel":0.0},"cca_rate":null,"belief_bounds":{"min_c":30.369140625,"max_c":30.369140625,"min_b":0.0048828125,"max_b":0.0048828125,"min_if":0.01904296875,"max_if":0.01904296875},"metrics":{"loss":83.009765625,"neg_delivered":-131.484375,"qdel":0.0,"shrink_c":true,"shrink_b":true,"shrink_maxc_mul":false,"shrink_maxc_add":false,"shrink_minc_mul":true,"shrink_minc_add":true},"chosen_move":null,"chosen_value":null},"children":[]},{"data":{"observation":{"a":413.69873046875,"s":233.669921875,"ld":180.0,"qdel":0.0},"cca_rate":null,"belief_bounds":{"min_c":30.341796875,"max_c":120.0,"min_b":0.0283203125,"max_b":120.0,"min_if":0.02880859375,"max_if":0.02880859375},"metrics":{"loss":83.0,"neg_delivered":-131.484375,"qdel":0.0,"shrink_c":false,"shrink_b":false,"shrink_maxc_mul":false,"shrink_maxc_add":false,"shrink_minc_mul":true,"shrink_minc_add":true},"chosen_move":null,"chosen_value":null},"children":[]}]},{"data":{"observation":{"a":398.52783203125,"s":218.4853515625,"ld":180.0,"qdel":0.0},"cca_rate":120.0,"belief_bounds":{"min_c":30.341796875,"max_c":120.0,"min_b":0.0419921875,"max_b":120.0,"min_if":0.04248046875,"max_if":0.04248046875},"metrics":{"loss":84.0,"neg_delivered":-116.2998046875,"qdel":0.0,"shrink_c":false,"shrink_b":false,"shrink_maxc_mul":false,"shrink_maxc_add":false,"shrink_minc_mul":true,"shrink_minc_add":true},"chosen_move":{"Network":{"ld":180.041015625,"s":218.4853515625,"qdel":0.0}},"chosen_value":{"Value":{"belief_bounds":{"min_c":30.34130859375,"max_c":30.34130859375,"min_b":0.0009765625,"max_b":0.0009765625,"min_if":30.34228515625,"max_if":30.34228515625},"metrics":{"loss":83.041015625,"neg_delivered":-116.2998046875,"qdel":0.0,"shrink_c":true,"shrink_b":true,"shrink_maxc_mul":false,"shrink_maxc_add":false,"shrink_minc_mul":true,"shrink_minc_add":true}}}},"children":[{"data":{"observation":{"a":518.52783203125,"s":338.513671875,"ld":180.009765625,"qdel":0.0},"cca_rate":null,"belief_bounds":{"min_c":119.986328125,"max_c":119.986328125,"min_b":0.0009765625,"max_b":0.0009765625,"min_if":0.00146484375,"max_if":0.00439453125},"metrics":{"loss":83.009765625,"neg_delivered":-236.328125,"qdel":0.0,"shrink_c":true,"shrink_b":true,"shrink_maxc_mul":false,"shrink_maxc_add":false,"shrink_minc_mul":true,"shrink_minc_add":true},"chosen_move":null,"chosen_value":null},"children":[]},{"data":{"observation":{"a":518.52783203125,"s":338.513671875,"ld":180.0,"qdel":0.0},"cca_rate":null,"belief_bounds":{"min_c":119.986328125,"max_c":120.0,"min_b":0.013671875,"max_b":120.0,"min_if":0.01416015625,"max_if":0.01416015625},"metrics":{"loss":83.0,"neg_delivered":-236.328125,"qdel":0.0,"shrink_c":true,"shrink_b":false,"shrink_maxc_mul":false,"shrink_maxc_add":false,"shrink_minc_mul":true,"shrink_minc_add":true},"chosen_move":null,"chosen_value":null},"children":[]},{"data":{"observation":{"a":518.52783203125,"s":218.4853515625,"ld":180.041015625,"qdel":0.0},"cca_rate":null,"belief_bounds":{"min_c":30.34130859375,"max_c":30.34130859375,"min_b":0.0009765625,"max_b":0.0009765625,"min_if":30.34228515625,"max_if":30.34228515625},"metrics":{"loss":83.041015625,"neg_delivered":-116.2998046875,"qdel":0.0,"shrink_c":true,"shrink_b":true,"shrink_maxc_mul":false,"shrink_maxc_add":false,"shrink_minc_mul":true,"shrink_minc_add":true},"chosen_move":null,"chosen_value":null},"children":[]},{"data":{"observation":{"a":518.52783203125,"s":218.4853515625,"ld":180.0,"qdel":0.0},"cca_rate":null,"belief_bounds":{"min_c":30.34130859375,"max_c":30.34130859375,"min_b":0.009765625,"max_b":120.0,"min_if":30.36376953125,"max_if":120.04248046875},"metrics":{"loss":83.0,"neg_delivered":-116.2998046875,"qdel":0.0,"shrink_c":true,"shrink_b":false,"shrink_maxc_mul":false,"shrink_maxc_add":false,"shrink_minc_mul":true,"shrink_minc_add":true},"chosen_move":null,"chosen_value":null},"children":[]}]},{"data":{"observation":{"a":398.52783203125,"s":218.4853515625,"ld":180.0,"qdel":0.0},"cca_rate":31.341796875,"belief_bounds":{"min_c":30.341796875,"max_c":120.0,"min_b":0.0419921875,"max_b":120.0,"min_if":0.04248046875,"max_if":0.04248046875},"metrics":{"loss":84.0,"neg_delivered":-116.2998046875,"qdel":0.0,"shrink_c":false,"shrink_b":false,"shrink_maxc_mul":false,"shrink_maxc_add":false,"shrink_minc_mul":true,"shrink_minc_add":true},"chosen_move":{"Network":{"ld":180.0,"s":249.8662109375,"qdel":0.0}},"chosen_value":{"Value":{"belief_bounds":{"min_c":31.3388671875,"max_c":120.0,"min_b":0.0029296875,"max_b":120.0,"min_if":0.00341796875,"max_if":0.00341796875},"metrics":{"loss":83.0,"neg_delivered":-147.6806640625,"qdel":0.0,"shrink_c":false,"shrink_b":false,"shrink_maxc_mul":false,"shrink_maxc_add":false,"shrink_minc_mul":true,"shrink_minc_add":true}}}},"children":[{"data":{"observation":{"a":429.86962890625,"s":249.8662109375,"ld":180.001953125,"qdel":0.0},"cca_rate":null,"belief_bounds":{"min_c":31.3388671875,"max_c":31.3388671875,"min_b":0.0009765625,"max_b":0.0009765625,"min_if":0.00146484375,"max_if":0.00146484375},"metrics":{"loss":83.001953125,"neg_delivered":-147.6806640625,"qdel":0.0,"shrink_c":true,"shrink_b":true,"shrink_maxc_mul":false,"shrink_maxc_add":false,"shrink_minc_mul":true,"shrink_minc_add":true},"chosen_move":null,"chosen_value":null},"children":[]},{"data":{"observation":{"a":429.86962890625,"s":249.8662109375,"ld":180.0,"qdel":0.0},"cca_rate":null,"belief_bounds":{"min_c":31.3388671875,"max_c":120.0,"min_b":0.0029296875,"max_b":120.0,"min_if":0.00341796875,"max_if":0.00341796875},"metrics":{"loss":83.0,"neg_delivered":-147.6806640625,"qdel":0.0,"shrink_c":false,"shrink_b":false,"shrink_maxc_mul":false,"shrink_maxc_add":false,"shrink_minc_mul":true,"shrink_minc_add":true},"chosen_move":null,"chosen_value":null},"children":[]}]},{"data":{"observation":{"a":398.52783203125,"s":218.4853515625,"ld":180.0,"qdel":0.0},"cca_rate":60.68359375,"belief_bounds":{"min_c":30.341796875,"max_c":120.0,"min_b":0.0419921875,"max_b":120.0,"min_if":0.04248046875,"max_if":0.04248046875},"metrics":{"loss":84.0,"neg_delivered":-116.2998046875,"qdel":0.0,"shrink_c":false,"shrink_b":false,"shrink_maxc_mul":false,"shrink_maxc_add":false,"shrink_minc_mul":true,"shrink_minc_add":true},"chosen_move":{"Network":{"ld":180.0,"s":279.205078125,"qdel":0.0}},"chosen_value":{"Value":{"belief_bounds":{"min_c":60.677734375,"max_c":120.0,"min_b":0.005859375,"max_b":120.0,"min_if":0.00634765625,"max_if":0.00634765625},"metrics":{"loss":83.0,"neg_delivered":-177.01953125,"qdel":0.0,"shrink_c":false,"shrink_b":false,"shrink_maxc_mul":false,"shrink_maxc_add":false,"shrink_minc_mul":true,"shrink_minc_add":true}}}},"children":[{"data":{"observation":{"a":459.21142578125,"s":279.205078125,"ld":180.00390625,"qdel":0.0},"cca_rate":null,"belief_bounds":{"min_c":60.677734375,"max_c":60.677734375,"min_b":0.0009765625,"max_b":0.0009765625,"min_if":0.00146484375,"max_if":0.00244140625},"metrics":{"loss":83.00390625,"neg_delivered":-177.01953125,"qdel":0.0,"shrink_c":true,"shrink_b":true,"shrink_maxc_mul":false,"shrink_maxc_add":false,"shrink_minc_mul":true,"shrink_minc_add":true},"chosen_move":null,"chosen_value":null},"children":[]},{"data":{"observation":{"a":459.21142578125,"s":279.205078125,"ld":180.0,"qdel":0.0},"cca_rate":null,"belief_bounds":{"min_c":60.677734375,"max_c":120.0,"min_b":0.005859375,"max_b":120.0,"min_if":0.00634765625,"max_if":0.00634765625},"metrics":{"loss":83.0,"neg_delivered":-177.01953125,"qdel":0.0,"shrink_c":false,"shrink_b":false,"shrink_maxc_mul":false,"shrink_maxc_add":false,"shrink_minc_mul":true,"shrink_minc_add":true},"chosen_move":null,"chosen_value":null},"children":[]}]},{"data":{"observation":{"a":398.52783203125,"s":218.4853515625,"ld":180.0,"qdel":0.0},"cca_rate":30.341796875,"belief_bounds":{"min_c":30.341796875,"max_c":120.0,"min_b":0.0419921875,"max_b":120.0,"min_if":0.04248046875,"max_if":0.04248046875},"metrics":{"loss":84.0,"neg_delivered":-116.2998046875,"qdel":0.0,"shrink_c":false,"shrink_b":false,"shrink_maxc_mul":false,"shrink_maxc_add":false,"shrink_minc_mul":true,"shrink_minc_add":true},"chosen_move":{"Network":{"ld":180.0,"s":248.8623046875,"qdel":0.0}},"chosen_value":{"Value":{"belief_bounds":{"min_c":30.359375,"max_c":120.0,"min_b":0.0068359375,"max_b":120.0,"min_if":0.00732421875,"max_if":0.00732421875},"metrics":{"loss":83.0,"neg_delivered":-146.6767578125,"qdel":0.0,"shrink_c":false,"shrink_b":false,"shrink_maxc_mul":false,"shrink_maxc_add":false,"shrink_minc_mul":true,"shrink_minc_add":true}}}},"children":[{"data":{"observation":{"a":428.86962890625,"s":248.8623046875,"ld":180.0,"qdel":0.0},"cca_rate":null,"belief_bounds":{"min_c":30.359375,"max_c":120.0,"min_b":0.0068359375,"max_b":120.0,"min_if":0.00732421875,"max_if":0.00732421875},"metrics":{"loss":83.0,"neg_delivered":-146.6767578125,"qdel":0.0,"shrink_c":false,"shrink_b":false,"shrink_maxc_mul":false,"shrink_maxc_add":false,"shrink_minc_mul":true,"shrink_minc_add":true},"chosen_move":null,"chosen_value":null},"children":[]}]}]},{"data":{"observation":{"a":398.52783203125,"s":170.99609375,"ld":180.0,"qdel":1.0},"cca_rate":null,"belief_bounds":{"min_c":11.6015625,"max_c":11.6015625,"min_b":11.5859375,"max_b":120.0,"min_if":23.16357421875,"max_if":47.53173828125},"metrics":{"loss":84.0,"neg_delivered":-68.810546875,"qdel":0.0,"shrink_c":true,"shrink_b":false,"shrink_maxc_mul":true,"shrink_maxc_add":true,"shrink_minc_mul":false,"shrink_minc_add":false},"chosen_move":{"CCA":{"rate":12.6015625}},"chosen_value":{"Value":{"belief_bounds":{"min_c":11.5751953125,"max_c":11.5751953125,"min_b":11.5859375,"max_b":11.6318359375,"min_if":11.58935546875,"max_if":11.63427734375},"metrics":{"loss":107.32421875,"neg_delivered":-91.9599609375,"qdel":0.0,"shrink_c":true,"shrink_b":true,"shrink_maxc_mul":true,"shrink_maxc_add":true,"shrink_minc_mul":false,"shrink_minc_add":false}}}},"children":[{"data":{"observation":{"a":398.52783203125,"s":170.99609375,"ld":180.0,"qdel":1.0},"cca_rate":5.80078125,"belief_bounds":{"min_c":11.6015625,"max_c":11.6015625,"min_b":11.5859375,"max_b":120.0,"min_if":23.16357421875,"max_if":47.53173828125},"metrics":{"loss":84.0,"neg_delivered":-68.810546875,"qdel":0.0,"shrink_c":true,"shrink_b":false,"shrink_maxc_mul":true,"shrink_maxc_add":true,"shrink_minc_mul":false,"shrink_minc_add":false},"chosen_move":{"Network":{"ld":204.33203125,"s":194.185546875,"qdel":1.0}},"chosen_value":{"Value":{"belief_bounds":{"min_c":11.5966796875,"max_c":11.5966796875,"min_b":11.6025390625,"max_b":11.6025390625,"min_if":5.80712890625,"max_if":5.81103515625},"metrics":{"loss":107.33203125,"neg_delivered":-92.0,"qdel":0.0,"shrink_c":true,"shrink_b":true,"shrink_maxc_mul":true,"shrink_maxc_add":true,"shrink_minc_mul":false,"shrink_minc_add":false}}}},"children":[{"data":{"observation":{"a":404.32861328125,"s":194.185546875,"ld":204.33203125,"qdel":1.0},"cca_rate":null,"belief_bounds":{"min_c":11.5966796875,"max_c":11.5966796875,"min_b":11.6025390625,"max_b":11.6025390625,"min_if":5.80712890625,"max_if":5.81103515625},"metrics":{"loss":107.33203125,"neg_delivered":-92.0,"qdel":0.0,"shrink_c":true,"shrink_b":true,"shrink_maxc_mul":true,"shrink_maxc_add":true,"shrink_minc_mul":false,"shrink_minc_add":false},"chosen_move":null,"chosen_value":null},"children":[]}]},{"data":{"observation":{"a":398.52783203125,"s":170.99609375,"ld":180.0,"qdel":1.0},"cca_rate":12.6015625,"belief_bounds":{"min_c":11.6015625,"max_c":11.6015625,"min_b":11.5859375,"max_b":120.0,"min_if":23.16357421875,"max_if":47.53173828125},"metrics":{"loss":84.0,"neg_delivered":-68.810546875,"qdel":0.0,"shrink_c":true,"shrink_b":false,"shrink_maxc_mul":true,"shrink_maxc_add":true,"shrink_minc_mul":false,"shrink_minc_add":false},"chosen_move":{"Network":{"ld":204.32421875,"s":194.1455078125,"qdel":1.0}},"chosen_value":{"Value":{"belief_bounds":{"min_c":11.5751953125,"max_c":11.5751953125,"min_b":11.5859375,"max_b":11.6318359375,"min_if":11.58935546875,"max_if":11.63427734375},"metrics":{"loss":107.32421875,"neg_delivered":-91.9599609375,"qdel":0.0,"shrink_c":true,"shrink_b":true,"shrink_maxc_mul":true,"shrink_maxc_add":true,"shrink_minc_mul":false,"shrink_minc_add":false}}}},"children":[{"data":{"observation":{"a":411.12939453125,"s":194.1455078125,"ld":204.32421875,"qdel":1.0},"cca_rate":null,"belief_bounds":{"min_c":11.5751953125,"max_c":11.5751953125,"min_b":11.5859375,"max_b":11.6318359375,"min_if":11.58935546875,"max_if":11.63427734375},"metrics":{"loss":107.32421875,"neg_delivered":-91.9599609375,"qdel":0.0,"shrink_c":true,"shrink_b":true,"shrink_maxc_mul":true,"shrink_maxc_add":true,"shrink_minc_mul":false,"shrink_minc_add":false},"chosen_move":null,"chosen_value":null},"children":[]}]},{"data":{"observation":{"a":398.52783203125,"s":170.99609375,"ld":180.0,"qdel":1.0},"cca_rate":23.203125,"belief_bounds":{"min_c":11.6015625,"max_c":11.6015625,"min_b":11.5859375,"max_b":120.0,"min_if":23.16357421875,"max_if":47.53173828125},"metrics":{"loss":84.0,"neg_delivered":-68.810546875,"qdel":0.0,"shrink_c":true,"shrink_b":false,"shrink_maxc_mul":true,"shrink_maxc_add":true,"shrink_minc_mul":false,"shrink_minc_add":false},"chosen_move":{"Network":{"ld":204.3310546875,"s":194.1630859375,"qdel":1.0}},"chosen_value":{"Value":{"belief_bounds":{"min_c":11.5888671875,"max_c":11.5888671875,"min_b":11.5654296875,"max_b":11.611328125,"min_if":11.61181640625,"max_if":11.61181640625},"metrics":{"loss":107.3310546875,"neg_delivered":-91.9775390625,"qdel":0.0,"shrink_c":true,"shrink_b":true,"shrink_maxc_mul":true,"shrink_maxc_add":true,"shrink_minc_mul":false,"shrink_minc_add":false}}}},"children":[{"data":{"observation":{"a":421.73095703125,"s":194.1630859375,"ld":204.3310546875,"qdel":1.0},"cca_rate":null,"belief_bounds":{"min_c":11.5888671875,"max_c":11.5888671875,"min_b":11.5654296875,"max_b":11.611328125,"min_if":11.61181640625,"max_if":11.61181640625},"metrics":{"loss":107.3310546875,"neg_delivered":-91.9775390625,"qdel":0.0,"shrink_c":true,"shrink_b":true,"shrink_maxc_mul":true,"shrink_maxc_add":true,"shrink_minc_mul":false,"shrink_minc_add":false},"chosen_move":null,"chosen_value":null},"children":[]}]},{"data":{"observation":{"a":398.52783203125,"s":170.99609375,"ld":180.0,"qdel":1.0},"cca_rate":11.6015625,"belief_bounds":{"min_c":11.6015625,"max_c":11.6015625,"min_b":11.5859375,"max_b":120.0,"min_if":23.16357421875,"max_if":47.53173828125},"metrics":{"loss":84.0,"neg_delivered":-68.810546875,"qdel":0.0,"shrink_c":true,"shrink_b":false,"shrink_maxc_mul":true,"shrink_maxc_add":true,"shrink_minc_mul":false,"shrink_minc_add":false},"chosen_move":{"Network":{"ld":204.3271484375,"s":194.1875,"qdel":1.0}},"chosen_value":{"Value":{"belief_bounds":{"min_c":11.59765625,"max_c":11.59765625,"min_b":11.59375,"max_b":11.59375,"min_if":11.60205078125,"max_if":11.61474609375},"metrics":{"loss":107.3271484375,"neg_delivered":-92.001953125,"qdel":0.0,"shrink_c":true,"shrink_b":true,"shrink_maxc_mul":true,"shrink_maxc_add":true,"shrink_minc_mul":false,"shrink_minc_add":false}}}},"children":[{"data":{"observation":{"a":410.12939453125,"s":194.1875,"ld":204.3271484375,"qdel":1.0},"cca_rate":null,"belief_bounds":{"min_c":11.59765625,"max_c":11.59765625,"min_b":11.59375,"max_b":11.59375,"min_if":11.60205078125,"max_if":11.61474609375},"metrics":{"loss":107.3271484375,"neg_delivered":-92.001953125,"qdel":0.0,"shrink_c":true,"shrink_b":true,"shrink_maxc_mul":true,"shrink_maxc_add":true,"shrink_minc_mul":false,"shrink_minc_add":false},"chosen_move":null,"chosen_value":null},"children":[]}]}]}]},{"data":{"observation":{"a":368.14404296875,"s":164.947265625,"ld":180.0,"qdel":0.0},"cca_rate":12.623046875,"belief_bounds":{"min_c":11.623046875,"max_c":30.3837890625,"min_b":10.0,"max_b":25.2001953125,"min_if":23.19677734375,"max_if":23.19677734375},"metrics":{"loss":85.0,"neg_delivered":-62.76171875,"qdel":0.0,"shrink_c":false,"shrink_b":false,"shrink_maxc_mul":false,"shrink_maxc_add":false,"shrink_minc_mul":false,"shrink_minc_add":false},"chosen_move":{"Network":{"ld":180.0,"s":170.99609375,"qdel":1.0}},"chosen_value":{"Value":{"belief_bounds":{"min_c":11.5771484375,"max_c":11.5771484375,"min_b":11.5771484375,"max_b":11.6298828125,"min_if":5.80810546875,"max_if":5.85302734375},"metrics":{"loss":89.564453125,"neg_delivered":-91.96484375,"qdel":0.0,"shrink_c":true,"shrink_b":true,"shrink_maxc_mul":true,"shrink_maxc_add":true,"shrink_minc_mul":false,"shrink_minc_add":false}}}},"children":[{"data":{"observation":{"a":380.76708984375,"s":200.744140625,"ld":180.0,"qdel":0.0},"cca_rate":null,"belief_bounds":{"min_c":17.9091796875,"max_c":120.0,"min_b":0.0625,"max_b":120.0,"min_if":0.02294921875,"max_if":0.02294921875},"metrics":{"loss":84.0,"neg_delivered":-98.55859375,"qdel":0.0,"shrink_c":false,"shrink_b":false,"shrink_maxc_mul":false,"shrink_maxc_add":false,"shrink_minc_mul":false,"shrink_minc_add":true},"chosen_move":{"CCA":{"rate":120.0}},"chosen_value":{"Value":{"belief_bounds":{"min_c":17.9033203125,"max_c":18.7080078125,"min_b":5.34375,"max_b":120.0,"min_if":23.20947265625,"max_if":120.02294921875},"metrics":{"loss":83.0,"neg_delivered":-98.55859375,"qdel":0.0,"shrink_c":true,"shrink_b":false,"shrink_maxc_mul":false,"shrink_maxc_add":true,"shrink_minc_mul":false,"shrink_minc_add":true}}}},"children":[{"data":{"observation":{"a":380.76708984375,"s":200.744140625,"ld":180.0,"qdel":0.0},"cca_rate":8.95458984375,"belief_bounds":{"min_c":17.9091796875,"max_c":120.0,"min_b":0.0625,"max_b":120.0,"min_if":0.02294921875,"max_if":0.02294921875},"metrics":{"loss":84.0,"neg_delivered":-98.55859375,"qdel":0.0,"shrink_c":false,"shrink_b":false,"shrink_maxc_mul":false,"shrink_maxc_add":false,"shrink_minc_mul":false,"shrink_minc_add":true},"chosen_move":{"Network":{"ld":180.0,"s":209.7041015625,"qdel":0.0}},"chosen_value":{"Value":{"belief_bounds":{"min_c":17.9033203125,"max_c":120.0,"min_b":0.0625,"max_b":120.0,"min_if":0.017578125,"max_if":0.017578125},"metrics":{"loss":83.0,"neg_delivered":-107.5185546875,"qdel":0.0,"shrink_c":false,"shrink_b":false,"shrink_maxc_mul":false,"shrink_maxc_add":false,"shrink_minc_mul":false,"shrink_minc_add":true}}}},"children":[{"data":{"observation":{"a":389.7216796875,"s":209.7041015625,"ld":180.0,"qdel":0.0},"cca_rate":null,"belief_bounds":{"min_c":17.9033203125,"max_c":120.0,"min_b":0.0625,"max_b":120.0,"min_if":0.017578125,"max_if":0.017578125},"metrics":{"loss":83.0,"neg_delivered":-107.5185546875,"qdel":0.0,"shrink_c":false,"shrink_b":false,"shrink_maxc_mul":false,"shrink_maxc_add":false,"shrink_minc_mul":false,"shrink_minc_add":true},"chosen_move":null,"chosen_value":null},"children":[]}]},{"data":{"observation":{"a":380.76708984375,"s":200.744140625,"ld":180.0,"qdel":0.0},"cca_rate":120.0,"belief_bounds":{"min_c":17.9091796875,"max_c":120.0,"min_b":0.0625,"max_b":120.0,"min_if":0.02294921875,"max_if":0.02294921875},"metrics":{"loss":84.0,"neg_delivered":-98.55859375,"qdel":0.0,"shrink_c":false,"shrink_b":false,"shrink_maxc_mul":false,"shrink_maxc_add":false,"shrink_minc_mul":false,"shrink_minc_add":true},"chosen_move":{"Network":{"ld":180.0,"s":200.744140625,"qdel":0.0}},"chosen_value":{"Value":{"belief_bounds":{"min_c":17.9033203125,"max_c":18.7080078125,"min_b":5.34375,"max_b":120.0,"min_if":23.20947265625,"max_if":120.02294921875},"metrics":{"loss":83.0,"neg_delivered":-98.55859375,"qdel":0.0,"shrink_c":true,"shrink_b":false,"shrink_maxc_mul":false,"shrink_maxc_add":true,"shrink_minc_mul":false,"shrink_minc_add":true}}}},"children":[{"data":{"observation":{"a":500.76708984375,"s":320.7529296875,"ld":180.009765625,"qdel":0.0},"cca_rate":null,"belief_bounds":{"min_c":119.9873046875,"max_c":119.9873046875,"min_b":0.0029296875,"max_b":0.0029296875,"min_if":0.00439453125,"max_if":0.00439453125},"metrics":{"loss":83.009765625,"neg_delivered":-218.5673828125,"qdel":0.0,"shrink_c":true,"shrink_b":true,"shrink_maxc_mul":false,"shrink_maxc_add":false,"shrink_minc_mul":true,"shrink_minc_add":true},"chosen_move":null,"chosen_value":null},"children":[]},{"data":{"observation":{"a":500.76708984375,"s":320.7529296875,"ld":180.0,"qdel":0.0},"cca_rate":null,"belief_bounds":{"min_c":119.986328125,"max_c":120.0,"min_b":0.013671875,"max_b":120.0,"min_if":0.01416015625,"max_if":0.01416015625},"metrics":{"loss":83.0,"neg_delivered":-218.5673828125,"qdel":0.0,"shrink_c":true,"shrink_b":false,"shrink_maxc_mul":false,"shrink_maxc_add":false,"shrink_minc_mul":true,"shrink_minc_add":true},"chosen_move":null,"chosen_value":null},"children":[]},{"data":{"observation":{"a":500.76708984375,"s":200.744140625,"ld":180.0,"qdel":0.0},"cca_rate":null,"belief_bounds":{"min_c":17.9033203125,"max_c":18.7080078125,"min_b":5.34375,"max_b":120.0,"min_if":23.20947265625,"max_if":120.02294921875},"metrics":{"loss":83.0,"neg_delivered":-98.55859375,"qdel":0.0,"shrink_c":true,"shrink_b":false,"shrink_maxc_mul":false,"shrink_maxc_add":true,"shrink_minc_mul":false,"shrink_minc_add":true},"chosen_move":null,"chosen_value":null},"children":[]}]},{"data":{"observation":{"a":380.76708984375,"s":200.744140625,"ld":180.0,"qdel":0.0},"cca_rate":18.9091796875,"belief_bounds":{"min_c":17.9091796875,"max_c":120.0,"min_b":0.0625,"max_b":120.0,"min_if":0.02294921875,"max_if":0.02294921875},"metrics":{"loss":84.0,"neg_delivered":-98.55859375,"qdel":0.0,"shrink_c":false,"shrink_b":false,"shrink_maxc_mul":false,"shrink_maxc_add":false,"shrink_minc_mul":false,"shrink_minc_add":true},"chosen_move":{"Network":{"ld":180.0,"s":219.6435546875,"qdel":0.0}},"chosen_value":{"Value":{"belief_bounds":{"min_c":18.876953125,"max_c":120.0,"min_b":0.044921875,"max_b":120.0,"min_if":0.03271484375,"max_if":0.03271484375},"metrics":{"loss":83.0,"neg_delivered":-117.4580078125,"qdel":0.0,"shrink_c":false,"shrink_b":false,"shrink_maxc_mul":false,"shrink_maxc_add":false,"shrink_minc_mul":false,"shrink_minc_add":true}}}},"children":[{"data":{"observation":{"a":399.67626953125,"s":219.6435546875,"ld":180.0,"qdel":0.0},"cca_rate":null,"belief_bounds":{"min_c":18.876953125,"max_c":120.0,"min_b":0.044921875,"max_b":120.0,"min_if":0.03271484375,"max_if":0.03271484375},"metrics":{"loss":83.0,"neg_delivered":-117.4580078125,"qdel":0.0,"shrink_c":false,"shrink_b":false,"shrink_maxc_mul":false,"shrink_maxc_add":false,"shrink_minc_mul":false,"shrink_minc_add":true},"chosen_move":null,"chosen_value":null},"children":[]}]},{"data":{"observation":{"a":380.76708984375,"s":200.744140625,"ld":180.0,"qdel":0.0},"cca_rate":35.818359375,"belief_bounds":{"min_c":17.9091796875,"max_c":120.0,"min_b":0.0625,"max_b":120.0,"min_if":0.02294921875,"max_if":0.02294921875},"metrics":{"loss":84.0,"neg_delivered":-98.55859375,"qdel":0.0,"shrink_c":false,"shrink_b":false,"shrink_maxc_mul":false,"shrink_maxc_add":false,"shrink_minc_mul":false,"shrink_minc_add":true},"chosen_move":{"Network":{"ld":180.0,"s":236.5361328125,"qdel":0.0}},"chosen_value":{"Value":{"belief_bounds":{"min_c":35.76953125,"max_c":120.0,"min_b":0.048828125,"max_b":120.0,"min_if":0.04931640625,"max_if":0.04931640625},"metrics":{"loss":83.0,"neg_delivered":-134.3505859375,"qdel":0.0,"shrink_c":false,"shrink_b":false,"shrink_maxc_mul":false,"shrink_maxc_add":false,"shrink_minc_mul":true,"shrink_minc_add":true}}}},"children":[{"data":{"observation":{"a":416.58544921875,"s":236.5361328125,"ld":180.0,"qdel":0.0},"cca_rate":null,"belief_bounds":{"min_c":35.76953125,"max_c":120.0,"min_b":0.048828125,"max_b":120.0,"min_if":0.04931640625,"max_if":0.04931640625},"metrics":{"loss":83.0,"neg_delivered":-134.3505859375,"qdel":0.0,"shrink_c":false,"shrink_b":false,"shrink_maxc_mul":false,"shrink_maxc_add":false,"shrink_minc_mul":true,"shrink_minc_add":true},"chosen_move":null,"chosen_value":null},"children":[]}]},{"data":{"observation":{"a":380.76708984375,"s":200.744140625,"ld":180.0,"qdel":0.0},"cca_rate":17.9091796875,"belief_bounds":{"min_c":17.9091796875,"max_c":120.0,"min_b":0.0625,"max_b":120.0,"min_if":0.02294921875,"max_if":0.02294921875},"metrics":{"loss":84.0,"neg_delivered":-98.55859375,"qdel":0.0,"shrink_c":false,"shrink_b":false,"shrink_maxc_mul":false,"shrink_maxc_add":false,"shrink_minc_mul":false,"shrink_minc_add":true},"chosen_move":{"Network":{"ld":180.0,"s":218.638671875,"qdel":0.0}},"chosen_value":{"Value":{"belief_bounds":{"min_c":17.9111328125,"max_c":120.0,"min_b":0.037109375,"max_b":120.0,"min_if":0.03759765625,"max_if":0.03759765625},"metrics":{"loss":83.0,"neg_delivered":-116.453125,"qdel":0.0,"shrink_c":false,"shrink_b":false,"shrink_maxc_mul":false,"shrink_maxc_add":false,"shrink_minc_mul":false,"shrink_minc_add":true}}}},"children":[{"data":{"observation":{"a":398.67626953125,"s":218.638671875,"ld":180.0,"qdel":0.0},"cca_rate":null,"belief_bounds":{"min_c":17.9111328125,"max_c":120.0,"min_b":0.037109375,"max_b":120.0,"min_if":0.03759765625,"max_if":0.03759765625},"metrics":{"loss":83.0,"neg_delivered":-116.453125,"qdel":0.0,"shrink_c":false,"shrink_b":false,"shrink_maxc_mul":false,"shrink_maxc_add":false,"shrink_minc_mul":false,"shrink_minc_add":true},"chosen_move":null,"chosen_value":null},"children":[]}]}]},{"data":{"observation":{"a":380.76708984375,"s":170.99609375,"ld":180.0,"qdel":1.0},"cca_rate":null,"belief_bounds":{"min_c":11.6015625,"max_c":11.6015625,"min_b":11.6015625,"max_b":120.0,"min_if":23.20166015625,"max_if":29.77099609375},"metrics":{"loss":84.0,"neg_delivered":-68.810546875,"qdel":0.0,"shrink_c":true,"shrink_b":false,"shrink_maxc_mul":true,"shrink_maxc_add":true,"shrink_minc_mul":false,"shrink_minc_add":false},"chosen_move":{"CCA":{"rate":5.80078125}},"chosen_value":{"Value":{"belief_bounds":{"min_c":11.5771484375,"max_c":11.5771484375,"min_b":11.5771484375,"max_b":11.6298828125,"min_if":5.80810546875,"max_if":5.85302734375},"metrics":{"loss":89.564453125,"neg_delivered":-91.96484375,"qdel":0.0,"shrink_c":true,"shrink_b":true,"shrink_maxc_mul":true,"shrink_maxc_add":true,"shrink_minc_mul":false,"shrink_minc_add":false}}}},"children":[{"data":{"observation":{"a":380.76708984375,"s":170.99609375,"ld":180.0,"qdel":1.0},"cca_rate":5.80078125,"belief_bounds":{"min_c":11.6015625,"max_c":11.6015625,"min_b":11.6015625,"max_b":120.0,"min_if":23.20166015625,"max_if":29.77099609375},"metrics":{"loss":84.0,"neg_delivered":-68.810546875,"qdel":0.0,"shrink_c":true,"shrink_b":false,"shrink_maxc_mul":true,"shrink_maxc_add":true,"shrink_minc_mul":false,"shrink_minc_add":false},"chosen_move":{"Network":{"ld":186.564453125,"s":194.150390625,"qdel":1.0}},"chosen_value":{"Value":{"belief_bounds":{"min_c":11.5771484375,"max_c":11.5771484375,"min_b":11.5771484375,"max_b":11.6298828125,"min_if":5.80810546875,"max_if":5.85302734375},"metrics":{"loss":89.564453125,"neg_delivered":-91.96484375,"qdel":0.0,"shrink_c":true,"shrink_b":true,"shrink_maxc_mul":true,"shrink_maxc_add":true,"shrink_minc_mul":false,"shrink_minc_add":false}}}},"children":[{"data":{"observation":{"a":386.56787109375,"s":194.150390625,"ld":186.564453125,"qdel":1.0},"cca_rate":null,"belief_bounds":{"min_c":11.5771484375,"max_c":11.5771484375,"min_b":11.5771484375,"max_b":11.6298828125,"min_if":5.80810546875,"max_if":5.85302734375},"metrics":{"loss":89.564453125,"neg_delivered":-91.96484375,"qdel":0.0,"shrink_c":true,"shrink_b":true,"shrink_maxc_mul":true,"shrink_maxc_add":true,"shrink_minc_mul":false,"shrink_minc_add":false},"chosen_move":null,"chosen_value":null},"children":[]}]},{"data":{"observation":{"a":380.76708984375,"s":170.99609375,"ld":180.0,"qdel":1.0},"cca_rate":12.6015625,"belief_bounds":{"min_c":11.6015625,"max_c":11.6015625,"min_b":11.6015625,"max_b":120.0,"min_if":23.20166015625,"max_if":29.77099609375},"metrics":{"loss":84.0,"neg_delivered":-68.810546875,"qdel":0.0,"shrink_c":true,"shrink_b":false,"shrink_maxc_mul":true,"shrink_maxc_add":true,"shrink_minc_mul":false,"shrink_minc_add":false},"chosen_move":{"Network":{"ld":186.5849609375,"s":194.173828125,"qdel":1.0}},"chosen_value":{"Value":{"belief_bounds":{"min_c":11.5927734375,"max_c":11.5927734375,"min_b":11.5849609375,"max_b":11.5849609375,"min_if":11.60986328125,"max_if":11.60986328125},"metrics":{"loss":89.5849609375,"neg_delivered":-91.98828125,"qdel":0.0,"shrink_c":true,"shrink_b":true,"shrink_maxc_mul":true,"shrink_maxc_add":true,"shrink_minc_mul":false,"shrink_minc_add":false}}}},"children":[{"data":{"observation":{"a":393.36865234375,"s":194.173828125,"ld":186.5849609375,"qdel":1.0},"cca_rate":null,"belief_bounds":{"min_c":11.5927734375,"max_c":11.5927734375,"min_b":11.5849609375,"max_b":11.5849609375,"min_if":11.60986328125,"max_if":11.60986328125},"metrics":{"loss":89.5849609375,"neg_delivered":-91.98828125,"qdel":0.0,"shrink_c":true,"shrink_b":true,"shrink_maxc_mul":true,"shrink_maxc_add":true,"shrink_minc_mul":false,"shrink_minc_add":false},"chosen_move":null,"chosen_value":null},"children":[]}]},{"data":{"observation":{"a":380.76708984375,"s":170.99609375,"ld":180.0,"qdel":1.0},"cca_rate":23.203125,"belief_bounds":{"min_c":11.6015625,"max_c":11.6015625,"min_b":11.6015625,"max_b":120.0,"min_if":23.20166015625,"max_if":29.77099609375},"metrics":{"loss":84.0,"neg_delivered":-68.810546875,"qdel":0.0,"shrink_c":true,"shrink_b":false,"shrink_maxc_mul":true,"shrink_maxc_add":true,"shrink_minc_mul":false,"shrink_minc_add":false},"chosen_move":{"Network":{"ld":186.572265625,"s":194.162109375,"qdel":1.0}},"chosen_value":{"Value":{"belief_bounds":{"min_c":11.5830078125,"max_c":11.5830078125,"min_b":11.5830078125,"max_b":11.5830078125,"min_if":11.58349609375,"max_if":11.62939453125},"metrics":{"loss":89.572265625,"neg_delivered":-91.9765625,"qdel":0.0,"shrink_c":true,"shrink_b":true,"shrink_maxc_mul":true,"shrink_maxc_add":true,"shrink_minc_mul":false,"shrink_minc_add":false}}}},"children":[{"data":{"observation":{"a":403.97021484375,"s":194.162109375,"ld":186.572265625,"qdel":1.0},"cca_rate":null,"belief_bounds":{"min_c":11.5830078125,"max_c":11.5830078125,"min_b":11.5830078125,"max_b":11.5830078125,"min_if":11.58349609375,"max_if":11.62939453125},"metrics":{"loss":89.572265625,"neg_delivered":-91.9765625,"qdel":0.0,"shrink_c":true,"shrink_b":true,"shrink_maxc_mul":true,"shrink_maxc_add":true,"shrink_minc_mul":false,"shrink_minc_add":false},"chosen_move":null,"chosen_value":null},"children":[]}]},{"data":{"observation":{"a":380.76708984375,"s":170.99609375,"ld":180.0,"qdel":1.0},"cca_rate":11.6015625,"belief_bounds":{"min_c":11.6015625,"max_c":11.6015625,"min_b":11.6015625,"max_b":120.0,"min_if":23.20166015625,"max_if":29.77099609375},"metrics":{"loss":84.0,"neg_delivered":-68.810546875,"qdel":0.0,"shrink_c":true,"shrink_b":false,"shrink_maxc_mul":true,"shrink_maxc_add":true,"shrink_minc_mul":false,"shrink_minc_add":false},"chosen_move":{"Network":{"ld":186.5888671875,"s":194.1513671875,"qdel":1.0}},"chosen_value":{"Value":{"belief_bounds":{"min_c":11.578125,"max_c":11.578125,"min_b":11.5771484375,"max_b":11.5771484375,"min_if":11.57861328125,"max_if":11.62841796875},"metrics":{"loss":89.5888671875,"neg_delivered":-91.9658203125,"qdel":0.0,"shrink_c":true,"shrink_b":true,"shrink_maxc_mul":true,"shrink_maxc_add":true,"shrink_minc_mul":false,"shrink_minc_add":false}}}},"children":[{"data":{"observation":{"a":392.36865234375,"s":194.1513671875,"ld":186.5888671875,"qdel":1.0},"cca_rate":null,"belief_bounds":{"min_c":11.578125,"max_c":11.578125,"min_b":11.5771484375,"max_b":11.5771484375,"min_if":11.57861328125,"max_if":11.62841796875},"metrics":{"loss":89.5888671875,"neg_delivered":-91.9658203125,"qdel":0.0,"shrink_c":true,"shrink_b":true,"shrink_maxc_mul":true,"shrink_maxc_add":true,"shrink_minc_mul":false,"shrink_minc_add":false},"chosen_move":null,"chosen_value":null},"children":[]}]}]}]},{"data":{"observation":{"a":368.14404296875,"s":164.947265625,"ld":180.0,"qdel":0.0},"cca_rate":23.24609375,"belief_bounds":{"min_c":11.623046875,"max_c":30.3837890625,"min_b":10.0,"max_b":25.2001953125,"min_if":23.19677734375,"max_if":23.19677734375},"metrics":{"loss":85.0,"neg_delivered":-62.76171875,"qdel":0.0,"shrink_c":false,"shrink_b":false,"shrink_maxc_mul":false,"shrink_maxc_add":false,"shrink_minc_mul":false,"shrink_minc_add":false},"chosen_move":{"Network":{"ld":180.0,"s":170.99609375,"qdel":1.0}},"chosen_value":{"Value":{"belief_bounds":{"min_c":11.578125,"max_c":11.578125,"min_b":11.5771484375,"max_b":11.6298828125,"min_if":11.58544921875,"max_if":11.63037109375},"metrics":{"loss":100.1943359375,"neg_delivered":-91.9658203125,"qdel":0.0,"shrink_c":true,"shrink_b":true,"shrink_maxc_mul":true,"shrink_maxc_add":true,"shrink_minc_mul":false,"shrink_minc_add":false}}}},"children":[{"data":{"observation":{"a":391.39013671875,"s":211.3623046875,"ld":180.0,"qdel":0.0},"cca_rate":null,"belief_bounds":{"min_c":23.21875,"max_c":120.0,"min_b":0.02734375,"max_b":120.0,"min_if":0.02783203125,"max_if":0.02783203125},"metrics":{"loss":84.0,"neg_delivered":-109.1767578125,"qdel":0.0,"shrink_c":false,"shrink_b":false,"shrink_maxc_mul":false,"shrink_maxc_add":false,"shrink_minc_mul":false,"shrink_minc_add":true},"chosen_move":{"CCA":{"rate":120.0}},"chosen_value":{"Value":{"belief_bounds":{"min_c":23.21826171875,"max_c":23.21826171875,"min_b":0.0205078125,"max_b":0.0205078125,"min_if":23.23876953125,"max_if":23.23876953125},"metrics":{"loss":83.0068359375,"neg_delivered":-109.1767578125,"qdel":0.0,"shrink_c":true,"shrink_b":true,"shrink_maxc_mul":false,"shrink_maxc_add":true,"shrink_minc_mul":false,"shrink_minc_add":true}}}},"children":[{"data":{"observation":{"a":391.39013671875,"s":211.3623046875,"ld":180.0,"qdel":0.0},"cca_rate":11.609375,"belief_bounds":{"min_c":23.21875,"max_c":120.0,"min_b":0.02734375,"max_b":120.0,"min_if":0.02783203125,"max_if":0.02783203125},"metrics":{"loss":84.0,"neg_delivered":-109.1767578125,"qdel":0.0,"shrink_c":false,"shrink_b":false,"shrink_maxc_mul":false,"shrink_maxc_add":false,"shrink_minc_mul":false,"shrink_minc_add":true},"chosen_move":{"Network":{"ld":180.0,"s":222.9794921875,"qdel":0.0}},"chosen_value":{"Value":{"belief_bounds":{"min_c":23.21875,"max_c":120.0,"min_b":0.01953125,"max_b":120.0,"min_if":0.02001953125,"max_if":0.02001953125},"metrics":{"loss":83.0,"neg_delivered":-120.7939453125,"qdel":0.0,"shrink_c":false,"shrink_b":false,"shrink_maxc_mul":false,"shrink_maxc_add":false,"shrink_minc_mul":false,"shrink_minc_add":true}}}},"children":[{"data":{"observation":{"a":402.99951171875,"s":222.9794921875,"ld":180.0068359375,"qdel":0.0},"cca_rate":null,"belief_bounds":{"min_c":23.21875,"max_c":23.21875,"min_b":0.0205078125,"max_b":0.0205078125,"min_if":0.01318359375,"max_if":0.01318359375},"metrics":{"loss":83.0068359375,"neg_delivered":-120.7939453125,"qdel":0.0,"shrink_c":true,"shrink_b":true,"shrink_maxc_mul":false,"shrink_maxc_add":true,"shrink_minc_mul":false,"shrink_minc_add":true},"chosen_move":null,"chosen_value":null},"children":[]},{"data":{"observation":{"a":402.99951171875,"s":222.9794921875,"ld":180.0,"qdel":0.0},"cca_rate":null,"belief_bounds":{"min_c":23.21875,"max_c":120.0,"min_b":0.01953125,"max_b":120.0,"min_if":0.02001953125,"max_if":0.02001953125},"metrics":{"loss":83.0,"neg_delivered":-120.7939453125,"qdel":0.0,"shrink_c":false,"shrink_b":false,"shrink_maxc_mul":false,"shrink_maxc_add":false,"shrink_minc_mul":false,"shrink_minc_add":true},"chosen_move":null,"chosen_value":null},"children":[]}]},{"data":{"observation":{"a":391.39013671875,"s":211.3623046875,"ld":180.0,"qdel":0.0},"cca_rate":120.0,"belief_bounds":{"min_c":23.21875,"max_c":120.0,"min_b":0.02734375,"max_b":120.0,"min_if":0.02783203125,"max_if":0.02783203125},"metrics":{"loss":84.0,"neg_delivered":-109.1767578125,"qdel":0.0,"shrink_c":false,"shrink_b":false,"shrink_maxc_mul":false,"shrink_maxc_add":false,"shrink_minc_mul":false,"shrink_minc_add":true},"chosen_move":{"Network":{"ld":180.0068359375,"s":211.3623046875,"qdel":0.0}},"chosen_value":{"Value":{"belief_bounds":{"min_c":23.21826171875,"max_c":23.21826171875,"min_b":0.0205078125,"max_b":0.0205078125,"min_if":23.23876953125,"max_if":23.23876953125},"metrics":{"loss":83.0068359375,"neg_delivered":-109.1767578125,"qdel":0.0,"shrink_c":true,"shrink_b":true,"shrink_maxc_mul":false,"shrink_maxc_add":true,"shrink_minc_mul":false,"shrink_minc_add":true}}}},"children":[{"data":{"observation":{"a":511.39013671875,"s":331.3759765625,"ld":180.0068359375,"qdel":0.0},"cca_rate":null,"belief_bounds":{"min_c":119.9892578125,"max_c":119.9892578125,"min_b":0.00390625,"max_b":0.00390625,"min_if":0.00732421875,"max_if":0.00732421875},"metrics":{"loss":83.0068359375,"neg_delivered":-229.1904296875,"qdel":0.0,"shrink_c":true,"shrink_b":true,"shrink_maxc_mul":false,"shrink_maxc_add":false,"shrink_minc_mul":true,"shrink_minc_add":true},"chosen_move":null,"chosen_value":null},"children":[]},{"data":{"observation":{"a":511.39013671875,"s":331.3759765625,"ld":180.0,"qdel":0.0},"cca_rate":null,"belief_bounds":{"min_c":119.986328125,"max_c":120.0,"min_b":0.013671875,"max_b":120.0,"min_if":0.01416015625,"max_if":0.01416015625},"metrics":{"loss":83.0,"neg_delivered":-229.1904296875,"qdel":0.0,"shrink_c":true,"shrink_b":false,"shrink_maxc_mul":false,"shrink_maxc_add":false,"shrink_minc_mul":true,"shrink_minc_add":true},"chosen_move":null,"chosen_value":null},"children":[]},{"data":{"observation":{"a":511.39013671875,"s":211.3623046875,"ld":180.0068359375,"qdel":0.0},"cca_rate":null,"belief_bounds":{"min_c":23.21826171875,"max_c":23.21826171875,"min_b":0.0205078125,"max_b":0.0205078125,"min_if":23.23876953125,"max_if":23.23876953125},"metrics":{"loss":83.0068359375,"neg_delivered":-109.1767578125,"qdel":0.0,"shrink_c":true,"shrink_b":true,"shrink_maxc_mul":false,"shrink_maxc_add":true,"shrink_minc_mul":false,"shrink_minc_add":true},"chosen_move":null,"chosen_value":null},"children":[]},{"data":{"observation":{"a":511.39013671875,"s":211.3623046875,"ld":180.0,"qdel":0.0},"cca_rate":null,"belief_bounds":{"min_c":23.21826171875,"max_c":23.21826171875,"min_b":0.0068359375,"max_b":120.0,"min_if":23.26904296875,"max_if":120.02783203125},"metrics":{"loss":83.0,"neg_delivered":-109.1767578125,"qdel":0.0,"shrink_c":true,"shrink_b":false,"shrink_maxc_mul":false,"shrink_maxc_add":true,"shrink_minc_mul":false,"shrink_minc_add":true},"chosen_move":null,"chosen_value":null},"children":[]}]},{"data":{"observation":{"a":391.39013671875,"s":211.3623046875,"ld":180.0,"qdel":0.0},"cca_rate":24.21875,"belief_bounds":{"min_c":23.21875,"max_c":120.0,"min_b":0.02734375,"max_b":120.0,"min_if":0.02783203125,"max_if":0.02783203125},"metrics":{"loss":84.0,"neg_delivered":-109.1767578125,"qdel":0.0,"shrink_c":false,"shrink_b":false,"shrink_maxc_mul":false,"shrink_maxc_add":false,"shrink_minc_mul":false,"shrink_minc_add":true},"chosen_move":{"Network":{"ld":180.0,"s":235.6083984375,"qdel":0.0}},"chosen_value":{"Value":{"belief_bounds":{"min_c":24.21875,"max_c":120.0,"min_b":0.0009765625,"max_b":120.0,"min_if":0.00048828125,"max_if":0.00048828125},"metrics":{"loss":83.0,"neg_delivered":-133.4228515625,"qdel":0.0,"shrink_c":false,"shrink_b":false,"shrink_maxc_mul":false,"shrink_maxc_add":false,"shrink_minc_mul":true,"shrink_minc_add":true}}}},"children":[{"data":{"observation":{"a":415.60888671875,"s":235.6083984375,"ld":180.0,"qdel":0.0},"cca_rate":null,"belief_bounds":{"min_c":24.21875,"max_c":120.0,"min_b":0.0009765625,"max_b":120.0,"min_if":0.00048828125,"max_if":0.00048828125},"metrics":{"loss":83.0,"neg_delivered":-133.4228515625,"qdel":0.0,"shrink_c":false,"shrink_b":false,"shrink_maxc_mul":false,"shrink_maxc_add":false,"shrink_minc_mul":true,"shrink_minc_add":true},"chosen_move":null,"chosen_value":null},"children":[]}]},{"data":{"observation":{"a":391.39013671875,"s":211.3623046875,"ld":180.0,"qdel":0.0},"cca_rate":46.4375,"belief_bounds":{"min_c":23.21875,"max_c":120.0,"min_b":0.02734375,"max_b":120.0,"min_if":0.02783203125,"max_if":0.02783203125},"metrics":{"loss":84.0,"neg_delivered":-109.1767578125,"qdel":0.0,"shrink_c":false,"shrink_b":false,"shrink_maxc_mul":false,"shrink_maxc_add":false,"shrink_minc_mul":false,"shrink_minc_add":true},"chosen_move":{"Network":{"ld":180.0,"s":257.7958984375,"qdel":0.0}},"chosen_value":{"Value":{"belief_bounds":{"min_c":46.40625,"max_c":120.0,"min_b":0.03125,"max_b":120.0,"min_if":0.03173828125,"max_if":0.03173828125},"metrics":{"loss":83.0,"neg_delivered":-155.6103515625,"qdel":0.0,"shrink_c":false,"shrink_b":false,"shrink_maxc_mul":false,"shrink_maxc_add":false,"shrink_minc_mul":true,"shrink_minc_add":true}}}},"children":[{"data":{"observation":{"a":437.82763671875,"s":257.7958984375,"ld":180.0234375,"qdel":0.0},"cca_rate":null,"belief_bounds":{"min_c":46.40625,"max_c":46.40625,"min_b":0.0078125,"max_b":0.0078125,"min_if":0.00830078125,"max_if":0.00830078125},"metrics":{"loss":83.0234375,"neg_delivered":-155.6103515625,"qdel":0.0,"shrink_c":true,"shrink_b":true,"shrink_maxc_mul":false,"shrink_maxc_add":false,"shrink_minc_mul":true,"shrink_minc_add":true},"chosen_move":null,"chosen_value":null},"children":[]},{"data":{"observation":{"a":437.82763671875,"s":257.7958984375,"ld":180.0,"qdel":0.0},"cca_rate":null,"belief_bounds":{"min_c":46.40625,"max_c":120.0,"min_b":0.03125,"max_b":120.0,"min_if":0.03173828125,"max_if":0.03173828125},"metrics":{"loss":83.0,"neg_delivered":-155.6103515625,"qdel":0.0,"shrink_c":false,"shrink_b":false,"shrink_maxc_mul":false,"shrink_maxc_add":false,"shrink_minc_mul":true,"shrink_minc_add":true},"chosen_move":null,"chosen_value":null},"children":[]}]},{"data":{"observation":{"a":391.39013671875,"s":211.3623046875,"ld":180.0,"qdel":0.0},"cca_rate":23.21875,"belief_bounds":{"min_c":23.21875,"max_c":120.0,"min_b":0.02734375,"max_b":120.0,"min_if":0.02783203125,"max_if":0.02783203125},"metrics":{"loss":84.0,"neg_delivered":-109.1767578125,"qdel":0.0,"shrink_c":false,"shrink_b":false,"shrink_maxc_mul":false,"shrink_maxc_add":false,"shrink_minc_mul":false,"shrink_minc_add":true},"chosen_move":{"Network":{"ld":180.0,"s":234.60546875,"qdel":0.0}},"chosen_value":{"Value":{"belief_bounds":{"min_c":23.2314453125,"max_c":120.0,"min_b":0.0029296875,"max_b":120.0,"min_if":0.00341796875,"max_if":0.00341796875},"metrics":{"loss":83.0,"neg_delivered":-132.419921875,"qdel":0.0,"shrink_c":false,"shrink_b":false,"shrink_maxc_mul":false,"shrink_maxc_add":false,"shrink_minc_mul":false,"shrink_minc_add":true}}}},"children":[{"data":{"observation":{"a":414.60888671875,"s":234.60546875,"ld":180.0,"qdel":0.0},"cca_rate":null,"belief_bounds":{"min_c":23.2314453125,"max_c":120.0,"min_b":0.0029296875,"max_b":120.0,"min_if":0.00341796875,"max_if":0.00341796875},"metrics":{"loss":83.0,"neg_delivered":-132.419921875,"qdel":0.0,"shrink_c":false,"shrink_b":false,"shrink_maxc_mul":false,"shrink_maxc_add":false,"shrink_minc_mul":false,"shrink_minc_add":true},"chosen_move":null,"chosen_value":null},"children":[]}]}]},{"data":{"observation":{"a":391.39013671875,"s":170.99609375,"ld":180.0,"qdel":1.0},"cca_rate":null,"belief_bounds":{"min_c":11.6015625,"max_c":11.6015625,"min_b":11.5732421875,"max_b":120.0,"min_if":23.19775390625,"max_if":40.39404296875},"metrics":{"loss":84.0,"neg_delivered":-68.810546875,"qdel":0.0,"shrink_c":true,"shrink_b":false,"shrink_maxc_mul":true,"shrink_maxc_add":true,"shrink_minc_mul":false,"shrink_minc_add":false},"chosen_move":{"CCA":{"rate":23.203125}},"chosen_value":{"Value":{"belief_bounds":{"min_c":11.578125,"max_c":11.578125,"min_b":11.5771484375,"max_b":11.6298828125,"min_if":11.58544921875,"max_if":11.63037109375},"metrics":{"loss":100.1943359375,"neg_delivered":-91.9658203125,"qdel":0.0,"shrink_c":true,"shrink_b":true,"shrink_maxc_mul":true,"shrink_maxc_add":true,"shrink_minc_mul":false,"shrink_minc_add":false}}}},"children":[{"data":{"observation":{"a":391.39013671875,"s":170.99609375,"ld":180.0,"qdel":1.0},"cca_rate":5.80078125,"belief_bounds":{"min_c":11.6015625,"max_c":11.6015625,"min_b":11.5732421875,"max_b":120.0,"min_if":23.19775390625,"max_if":40.39404296875},"metrics":{"loss":84.0,"neg_delivered":-68.810546875,"qdel":0.0,"shrink_c":true,"shrink_b":false,"shrink_maxc_mul":true,"shrink_maxc_add":true,"shrink_minc_mul":false,"shrink_minc_add":false},"chosen_move":{"Network":{"ld":197.234375,"s":194.1640625,"qdel":0.0}},"chosen_value":{"Value":{"belief_bounds":{"min_c":11.6015625,"max_c":11.6015625,"min_b":10.6083984375,"max_b":11.5576171875,"min_if":4.84326171875,"max_if":5.79248046875},"metrics":{"loss":100.234375,"neg_delivered":-91.978515625,"qdel":0.0,"shrink_c":true,"shrink_b":true,"shrink_maxc_mul":true,"shrink_maxc_add":true,"shrink_minc_mul":false,"shrink_minc_add":false}}}},"children":[{"data":{"observation":{"a":397.19091796875,"s":194.1640625,"ld":197.234375,"qdel":0.0},"cca_rate":null,"belief_bounds":{"min_c":11.6015625,"max_c":11.6015625,"min_b":10.6083984375,"max_b":11.5576171875,"min_if":4.84326171875,"max_if":5.79248046875},"metrics":{"loss":100.234375,"neg_delivered":-91.978515625,"qdel":0.0,"shrink_c":true,"shrink_b":true,"shrink_maxc_mul":true,"shrink_maxc_add":true,"shrink_minc_mul":false,"shrink_minc_add":false},"chosen_move":null,"chosen_value":null},"children":[]}]},{"data":{"observation":{"a":391.39013671875,"s":170.99609375,"ld":180.0,"qdel":1.0},"cca_rate":12.6015625,"belief_bounds":{"min_c":11.6015625,"max_c":11.6015625,"min_b":11.5732421875,"max_b":120.0,"min_if":23.19775390625,"max_if":40.39404296875},"metrics":{"loss":84.0,"neg_delivered":-68.810546875,"qdel":0.0,"shrink_c":true,"shrink_b":false,"shrink_maxc_mul":true,"shrink_maxc_add":true,"shrink_minc_mul":false,"shrink_minc_add":false},"chosen_move":{"Network":{"ld":197.2216796875,"s":194.1630859375,"qdel":1.0}},"chosen_value":{"Value":{"belief_bounds":{"min_c":11.583984375,"max_c":11.583984375,"min_b":11.587890625,"max_b":11.587890625,"min_if":11.58837890625,"max_if":11.58837890625},"metrics":{"loss":100.2216796875,"neg_delivered":-91.9775390625,"qdel":0.0,"shrink_c":true,"shrink_b":true,"shrink_maxc_mul":true,"shrink_maxc_add":true,"shrink_minc_mul":false,"shrink_minc_add":false}}}},"children":[{"data":{"observation":{"a":403.99169921875,"s":194.1630859375,"ld":197.2216796875,"qdel":1.0},"cca_rate":null,"belief_bounds":{"min_c":11.583984375,"max_c":11.583984375,"min_b":11.587890625,"max_b":11.587890625,"min_if":11.58837890625,"max_if":11.58837890625},"metrics":{"loss":100.2216796875,"neg_delivered":-91.9775390625,"qdel":0.0,"shrink_c":true,"shrink_b":true,"shrink_maxc_mul":true,"shrink_maxc_add":true,"shrink_minc_mul":false,"shrink_minc_add":false},"chosen_move":null,"chosen_value":null},"children":[]}]},{"data":{"observation":{"a":391.39013671875,"s":170.99609375,"ld":180.0,"qdel":1.0},"cca_rate":23.203125,"belief_bounds":{"min_c":11.6015625,"max_c":11.6015625,"min_b":11.5732421875,"max_b":120.0,"min_if":23.19775390625,"max_if":40.39404296875},"metrics":{"loss":84.0,"neg_delivered":-68.810546875,"qdel":0.0,"shrink_c":true,"shrink_b":false,"shrink_maxc_mul":true,"shrink_maxc_add":true,"shrink_minc_mul":false,"shrink_minc_add":false},"chosen_move":{"Network":{"ld":197.1943359375,"s":194.1513671875,"qdel":1.0}},"chosen_value":{"Value":{"belief_bounds":{"min_c":11.578125,"max_c":11.578125,"min_b":11.5771484375,"max_b":11.6298828125,"min_if":11.58544921875,"max_if":11.63037109375},"metrics":{"loss":100.1943359375,"neg_delivered":-91.9658203125,"qdel":0.0,"shrink_c":true,"shrink_b":true,"shrink_maxc_mul":true,"shrink_maxc_add":true,"shrink_minc_mul":false,"shrink_minc_add":false}}}},"children":[{"data":{"observation":{"a":414.59326171875,"s":194.1513671875,"ld":197.1943359375,"qdel":1.0},"cca_rate":null,"belief_bounds":{"min_c":11.578125,"max_c":11.578125,"min_b":11.5771484375,"max_b":11.6298828125,"min_if":11.58544921875,"max_if":11.63037109375},"metrics":{"loss":100.1943359375,"neg_delivered":-91.9658203125,"qdel":0.0,"shrink_c":true,"shrink_b":true,"shrink_maxc_mul":true,"shrink_maxc_add":true,"shrink_minc_mul":false,"shrink_minc_add":false},"chosen_move":null,"chosen_value":null},"children":[]}]},{"data":{"observation":{"a":391.39013671875,"s":170.99609375,"ld":180.0,"qdel":1.0},"cca_rate":11.6015625,"belief_bounds":{"min_c":11.6015625,"max_c":11.6015625,"min_b":11.5732421875,"max_b":120.0,"min_if":23.19775390625,"max_if":40.39404296875},"metrics":{"loss":84.0,"neg_delivered":-68.810546875,"qdel":0.0,"shrink_c":true,"shrink_b":false,"shrink_maxc_mul":true,"shrink_maxc_add":true,"shrink_minc_mul":false,"shrink_minc_add":false},"chosen_move":{"Network":{"ld":197.2314453125,"s":194.15625,"qdel":1.0}},"chosen_value":{"Value":{"belief_bounds":{"min_c":11.5869140625,"max_c":11.5869140625,"min_b":11.564453125,"max_b":11.564453125,"min_if":11.59619140625,"max_if":11.60400390625},"metrics":{"loss":100.2314453125,"neg_delivered":-91.970703125,"qdel":0.0,"shrink_c":true,"shrink_b":true,"shrink_maxc_mul":true,"shrink_maxc_add":true,"shrink_minc_mul":false,"shrink_minc_add":false}}}},"children":[{"data":{"observation":{"a":402.99169921875,"s":194.15625,"ld":197.2314453125,"qdel":1.0},"cca_rate":null,"belief_bounds":{"min_c":11.5869140625,"max_c":11.5869140625,"min_b":11.564453125,"max_b":11.564453125,"min_if":11.59619140625,"max_if":11.60400390625},"metrics":{"loss":100.2314453125,"neg_delivered":-91.970703125,"qdel":0.0,"shrink_c":true,"shrink_b":true,"shrink_maxc_mul":true,"shrink_maxc_add":true,"shrink_minc_mul":false,"shrink_minc_add":false},"chosen_move":null,"chosen_value":null},"children":[]}]}]}]},{"data":{"observation":{"a":368.14404296875,"s":164.947265625,"ld":180.0,"qdel":0.0},"cca_rate":11.623046875,"belief_bounds":{"min_c":11.623046875,"max_c":30.3837890625,"min_b":10.0,"max_b":25.2001953125,"min_if":23.19677734375,"max_if":23.19677734375},"metrics":{"loss":85.0,"neg_delivered":-62.76171875,"qdel":0.0,"shrink_c":false,"shrink_b":false,"shrink_maxc_mul":false,"shrink_maxc_add":false,"shrink_minc_mul":false,"shrink_minc_add":false},"chosen_move":{"Network":{"ld":180.0,"s":170.99609375,"qdel":1.0}},"chosen_value":{"Value":{"belief_bounds":{"min_c":11.6015625,"max_c":11.6015625,"min_b":11.623046875,"max_b":11.623046875,"min_if":11.62353515625,"max_if":11.62353515625},"metrics":{"loss":88.5458984375,"neg_delivered":-92.013671875,"qdel":0.0,"shrink_c":true,"shrink_b":true,"shrink_maxc_mul":true,"shrink_maxc_add":true,"shrink_minc_mul":false,"shrink_minc_add":false}}}},"children":[{"data":{"observation":{"a":379.76708984375,"s":199.7529296875,"ld":180.0,"qdel":0.0},"cca_rate":null,"belief_bounds":{"min_c":17.42578125,"max_c":120.0,"min_b":0.05859375,"max_b":120.0,"min_if":0.01416015625,"max_if":0.01416015625},"metrics":{"loss":84.0,"neg_delivered":-97.5673828125,"qdel":0.0,"shrink_c":false,"shrink_b":false,"shrink_maxc_mul":false,"shrink_maxc_add":false,"shrink_minc_mul":false,"shrink_minc_add":true},"chosen_move":{"CCA":{"rate":120.0}},"chosen_value":{"Value":{"belief_bounds":{"min_c":17.40625,"max_c":18.3564453125,"min_b":5.7978515625,"max_b":120.0,"min_if":23.20751953125,"max_if":120.01416015625},"metrics":{"loss":83.0,"neg_delivered":-97.5673828125,"qdel":0.0,"shrink_c":true,"shrink_b":false,"shrink_maxc_mul":false,"shrink_maxc_add":true,"shrink_minc_mul":false,"shrink_minc_add":true}}}},"children":[{"data":{"observation":{"a":379.76708984375,"s":199.7529296875,"ld":180.0,"qdel":0.0},"cca_rate":8.712890625,"belief_bounds":{"min_c":17.42578125,"max_c":120.0,"min_b":0.05859375,"max_b":120.0,"min_if":0.01416015625,"max_if":0.01416015625},"metrics":{"loss":84.0,"neg_delivered":-97.5673828125,"qdel":0.0,"shrink_c":false,"shrink_b":false,"shrink_maxc_mul":false,"shrink_maxc_add":false,"shrink_minc_mul":false,"shrink_minc_add":true},"chosen_move":{"Network":{"ld":180.0,"s":208.4638671875,"qdel":0.0}},"chosen_value":{"Value":{"belief_bounds":{"min_c":17.40625,"max_c":120.0,"min_b":0.015625,"max_b":120.0,"min_if":0.01611328125,"max_if":0.01611328125},"metrics":{"loss":83.0,"neg_delivered":-106.2783203125,"qdel":0.0,"shrink_c":false,"shrink_b":false,"shrink_maxc_mul":false,"shrink_maxc_add":false,"shrink_minc_mul":false,"shrink_minc_add":true}}}},"children":[{"data":{"observation":{"a":388.47998046875,"s":208.4638671875,"ld":180.0,"qdel":0.0},"cca_rate":null,"belief_bounds":{"min_c":17.40625,"max_c":120.0,"min_b":0.015625,"max_b":120.0,"min_if":0.01611328125,"max_if":0.01611328125},"metrics":{"loss":83.0,"neg_delivered":-106.2783203125,"qdel":0.0,"shrink_c":false,"shrink_b":false,"shrink_maxc_mul":false,"shrink_maxc_add":false,"shrink_minc_mul":false,"shrink_minc_add":true},"chosen_move":null,"chosen_value":null},"children":[]}]},{"data":{"observation":{"a":379.76708984375,"s":199.7529296875,"ld":180.0,"qdel":0.0},"cca_rate":120.0,"belief_bounds":{"min_c":17.42578125,"max_c":120.0,"min_b":0.05859375,"max_b":120.0,"min_if":0.01416015625,"max_if":0.01416015625},"metrics":{"loss":84.0,"neg_delivered":-97.5673828125,"qdel":0.0,"shrink_c":false,"shrink_b":false,"shrink_maxc_mul":false,"shrink_maxc_add":false,"shrink_minc_mul":false,"shrink_minc_add":true},"chosen_move":{"Network":{"ld":180.0,"s":199.7529296875,"qdel":0.0}},"chosen_value":{"Value":{"belief_bounds":{"min_c":17.40625,"max_c":18.3564453125,"min_b":5.7978515625,"max_b":120.0,"min_if":23.20751953125,"max_if":120.01416015625},"metrics":{"loss":83.0,"neg_delivered":-97.5673828125,"qdel":0.0,"shrink_c":true,"shrink_b":false,"shrink_maxc_mul":false,"shrink_maxc_add":true,"shrink_minc_mul":false,"shrink_minc_add":true}}}},"children":[{"data":{"observation":{"a":499.76708984375,"s":319.7529296875,"ld":180.0,"qdel":0.0},"cca_rate":null,"belief_bounds":{"min_c":119.986328125,"max_c":120.0,"min_b":0.013671875,"max_b":120.0,"min_if":0.01416015625,"max_if":0.01416015625},"metrics":{"loss":83.0,"neg_delivered":-217.5673828125,"qdel":0.0,"shrink_c":true,"shrink_b":false,"shrink_maxc_mul":false,"shrink_maxc_add":false,"shrink_minc_mul":true,"shrink_minc_add":true},"chosen_move":null,"chosen_value":null},"children":[]},{"data":{"observation":{"a":499.76708984375,"s":199.7529296875,"ld":180.0,"qdel":0.0},"cca_rate":null,"belief_bounds":{"min_c":17.40625,"max_c":18.3564453125,"min_b":5.7978515625,"max_b":120.0,"min_if":23.20751953125,"max_if":120.01416015625},"metrics":{"loss":83.0,"neg_delivered":-97.5673828125,"qdel":0.0,"shrink_c":true,"shrink_b":false,"shrink_maxc_mul":false,"shrink_maxc_add":true,"shrink_minc_mul":false,"shrink_minc_add":true},"chosen_move":null,"chosen_value":null},"children":[]}]},{"data":{"observation":{"a":379.76708984375,"s":199.7529296875,"ld":180.0,"qdel":0.0},"cca_rate":18.42578125,"belief_bounds":{"min_c":17.42578125,"max_c":120.0,"min_b":0.05859375,"max_b":120.0,"min_if":0.01416015625,"max_if":0.01416015625},"metrics":{"loss":84.0,"neg_delivered":-97.5673828125,"qdel":0.0,"shrink_c":false,"shrink_b":false,"shrink_maxc_mul":false,"shrink_maxc_add":false,"shrink_minc_mul":false,"shrink_minc_add":true},"chosen_move":{"Network":{"ld":180.0,"s":218.1650390625,"qdel":0.0}},"chosen_value":{"Value":{"belief_bounds":{"min_c":18.3984375,"max_c":120.0,"min_b":0.0517578125,"max_b":120.0,"min_if":0.02783203125,"max_if":0.02783203125},"metrics":{"loss":83.0,"neg_delivered":-115.9794921875,"qdel":0.0,"shrink_c":false,"shrink_b":false,"shrink_maxc_mul":false,"shrink_maxc_add":false,"shrink_minc_mul":false,"shrink_minc_add":true}}}},"children":[{"data":{"observation":{"a":398.19287109375,"s":218.1650390625,"ld":180.0,"qdel":0.0},"cca_rate":null,"belief_bounds":{"min_c":18.3984375,"max_c":120.0,"min_b":0.0517578125,"max_b":120.0,"min_if":0.02783203125,"max_if":0.02783203125},"metrics":{"loss":83.0,"neg_delivered":-115.9794921875,"qdel":0.0,"shrink_c":false,"shrink_b":false,"shrink_maxc_mul":false,"shrink_maxc_add":false,"shrink_minc_mul":false,"shrink_minc_add":true},"chosen_move":null,"chosen_value":null},"children":[]}]},{"data":{"observation":{"a":379.76708984375,"s":199.7529296875,"ld":180.0,"qdel":0.0},"cca_rate":34.8515625,"belief_bounds":{"min_c":17.42578125,"max_c":120.0,"min_b":0.05859375,"max_b":120.0,"min_if":0.01416015625,"max_if":0.01416015625},"metrics":{"loss":84.0,"neg_delivered":-97.5673828125,"qdel":0.0,"shrink_c":false,"shrink_b":false,"shrink_maxc_mul":false,"shrink_maxc_add":false,"shrink_minc_mul":false,"shrink_minc_add":true},"chosen_move":{"Network":{"ld":180.0,"s":234.59765625,"qdel":0.0}},"chosen_value":{"Value":{"belief_bounds":{"min_c":34.8310546875,"max_c":120.0,"min_b":0.0205078125,"max_b":120.0,"min_if":0.02099609375,"max_if":0.02099609375},"metrics":{"loss":83.0,"neg_delivered":-132.412109375,"qdel":0.0,"shrink_c":false,"shrink_b":false,"shrink_maxc_mul":false,"shrink_maxc_add":false,"shrink_minc_mul":true,"shrink_minc_add":true}}}},"children":[{"data":{"observation":{"a":414.61865234375,"s":234.59765625,"ld":180.0,"qdel":0.0},"cca_rate":null,"belief_bounds":{"min_c":34.8310546875,"max_c":120.0,"min_b":0.0205078125,"max_b":120.0,"min_if":0.02099609375,"max_if":0.02099609375},"metrics":{"loss":83.0,"neg_delivered":-132.412109375,"qdel":0.0,"shrink_c":false,"shrink_b":false,"shrink_maxc_mul":false,"shrink_maxc_add":false,"shrink_minc_mul":true,"shrink_minc_add":true},"chosen_move":null,"chosen_value":null},"children":[]}]},{"data":{"observation":{"a":379.76708984375,"s":199.7529296875,"ld":180.0,"qdel":0.0},"cca_rate":17.42578125,"belief_bounds":{"min_c":17.42578125,"max_c":120.0,"min_b":0.05859375,"max_b":120.0,"min_if":0.01416015625,"max_if":0.01416015625},"metrics":{"loss":84.0,"neg_delivered":-97.5673828125,"qdel":0.0,"shrink_c":false,"shrink_b":false,"shrink_maxc_mul":false,"shrink_maxc_add":false,"shrink_minc_mul":false,"shrink_minc_add":true},"chosen_move":{"Network":{"ld":180.0,"s":217.185546875,"qdel":0.0}},"chosen_value":{"Value":{"belief_bounds":{"min_c":17.4189453125,"max_c":120.0,"min_b":0.0625,"max_b":120.0,"min_if":0.00732421875,"max_if":0.00732421875},"metrics":{"loss":83.0,"neg_delivered":-115.0,"qdel":0.0,"shrink_c":false,"shrink_b":false,"shrink_maxc_mul":false,"shrink_maxc_add":false,"shrink_minc_mul":false,"shrink_minc_add":true}}}},"children":[{"data":{"observation":{"a":397.19287109375,"s":217.185546875,"ld":180.0,"qdel":0.0},"cca_rate":null,"belief_bounds":{"min_c":17.4189453125,"max_c":120.0,"min_b":0.0625,"max_b":120.0,"min_if":0.00732421875,"max_if":0.00732421875},"metrics":{"loss":83.0,"neg_delivered":-115.0,"qdel":0.0,"shrink_c":false,"shrink_b":false,"shrink_maxc_mul":false,"shrink_maxc_add":false,"shrink_minc_mul":false,"shrink_minc_add":true},"chosen_move":null,"chosen_value":null},"children":[]}]}]},{"data":{"observation":{"a":379.76708984375,"s":170.99609375,"ld":180.0,"qdel":1.0},"cca_rate":null,"belief_bounds":{"min_c":11.6015625,"max_c":11.6015625,"min_b":11.6015625,"max_b":120.0,"min_if":23.20947265625,"max_if":28.77099609375},"metrics":{"loss":84.0,"neg_delivered":-68.810546875,"qdel":0.0,"shrink_c":true,"shrink_b":false,"shrink_maxc_mul":true,"shrink_maxc_add":true,"shrink_minc_mul":false,"shrink_minc_add":false},"chosen_move":{"CCA":{"rate":12.6015625}},"chosen_value":{"Value":{"belief_bounds":{"min_c":11.6015625,"max_c":11.6015625,"min_b":11.623046875,"max_b":11.623046875,"min_if":11.62353515625,"max_if":11.62353515625},"metrics":{"loss":88.5458984375,"neg_delivered":-92.013671875,"qdel":0.0,"shrink_c":true,"shrink_b":true,"shrink_maxc_mul":true,"shrink_maxc_add":true,"shrink_minc_mul":false,"shrink_minc_add":false}}}},"children":[{"data":{"observation":{"a":379.76708984375,"s":170.99609375,"ld":180.0,"qdel":1.0},"cca_rate":5.80078125,"belief_bounds":{"min_c":11.6015625,"max_c":11.6015625,"min_b":11.6015625,"max_b":120.0,"min_if":23.20947265625,"max_if":28.77099609375},"metrics":{"loss":84.0,"neg_delivered":-68.810546875,"qdel":0.0,"shrink_c":true,"shrink_b":false,"shrink_maxc_mul":true,"shrink_maxc_add":true,"shrink_minc_mul":false,"shrink_minc_add":false},"chosen_move":{"Network":{"ld":185.5693359375,"s":194.173828125,"qdel":1.0}},"chosen_value":{"Value":{"belief_bounds":{"min_c":11.5888671875,"max_c":11.5888671875,"min_b":11.5888671875,"max_b":11.5888671875,"min_if":5.81396484375,"max_if":5.82470703125},"metrics":{"loss":88.5693359375,"neg_delivered":-91.98828125,"qdel":0.0,"shrink_c":true,"shrink_b":true,"shrink_maxc_mul":true,"shrink_maxc_add":true,"shrink_minc_mul":false,"shrink_minc_add":false}}}},"children":[{"data":{"observation":{"a":385.56787109375,"s":194.173828125,"ld":185.5693359375,"qdel":1.0},"cca_rate":null,"belief_bounds":{"min_c":11.5888671875,"max_c":11.5888671875,"min_b":11.5888671875,"max_b":11.5888671875,"min_if":5.81396484375,"max_if":5.82470703125},"metrics":{"loss":88.5693359375,"neg_delivered":-91.98828125,"qdel":0.0,"shrink_c":true,"shrink_b":true,"shrink_maxc_mul":true,"shrink_maxc_add":true,"shrink_minc_mul":false,"shrink_minc_add":false},"chosen_move":null,"chosen_value":null},"children":[]}]},{"data":{"observation":{"a":379.76708984375,"s":170.99609375,"ld":180.0,"qdel":1.0},"cca_rate":12.6015625,"belief_bounds":{"min_c":11.6015625,"max_c":11.6015625,"min_b":11.6015625,"max_b":120.0,"min_if":23.20947265625,"max_if":28.77099609375},"metrics":{"loss":84.0,"neg_delivered":-68.810546875,"qdel":0.0,"shrink_c":true,"shrink_b":false,"shrink_maxc_mul":true,"shrink_maxc_add":true,"shrink_minc_mul":false,"shrink_minc_add":false},"chosen_move":{"Network":{"ld":185.5458984375,"s":194.19921875,"qdel":1.0}},"chosen_value":{"Value":{"belief_bounds":{"min_c":11.6015625,"max_c":11.6015625,"min_b":11.623046875,"max_b":11.623046875,"min_if":11.62353515625,"max_if":11.62353515625},"metrics":{"loss":88.5458984375,"neg_delivered":-92.013671875,"qdel":0.0,"shrink_c":true,"shrink_b":true,"shrink_maxc_mul":true,"shrink_maxc_add":true,"shrink_minc_mul":false,"shrink_minc_add":false}}}},"children":[{"data":{"observation":{"a":392.36865234375,"s":194.19921875,"ld":185.5458984375,"qdel":1.0},"cca_rate":null,"belief_bounds":{"min_c":11.6015625,"max_c":11.6015625,"min_b":11.623046875,"max_b":11.623046875,"min_if":11.62353515625,"max_if":11.62353515625},"metrics":{"loss":88.5458984375,"neg_delivered":-92.013671875,"qdel":0.0,"shrink_c":true,"shrink_b":true,"shrink_maxc_mul":true,"shrink_maxc_add":true,"shrink_minc_mul":false,"shrink_minc_add":false},"chosen_move":null,"chosen_value":null},"children":[]}]},{"data":{"observation":{"a":379.76708984375,"s":170.99609375,"ld":180.0,"qdel":1.0},"cca_rate":23.203125,"belief_bounds":{"min_c":11.6015625,"max_c":11.6015625,"min_b":11.6015625,"max_b":120.0,"min_if":23.20947265625,"max_if":28.77099609375},"metrics":{"loss":84.0,"neg_delivered":-68.810546875,"qdel":0.0,"shrink_c":true,"shrink_b":false,"shrink_maxc_mul":true,"shrink_maxc_add":true,"shrink_minc_mul":false,"shrink_minc_add":false},"chosen_move":{"Network":{"ld":185.572265625,"s":194.1630859375,"qdel":1.0}},"chosen_value":{"Value":{"belief_bounds":{"min_c":11.583984375,"max_c":11.583984375,"min_b":11.615234375,"max_b":11.615234375,"min_if":11.61572265625,"max_if":11.61572265625},"metrics":{"loss":88.572265625,"neg_delivered":-91.9775390625,"qdel":0.0,"shrink_c":true,"shrink_b":true,"shrink_maxc_mul":true,"shrink_maxc_add":true,"shrink_minc_mul":false,"shrink_minc_add":false}}}},"children":[{"data":{"observation":{"a":402.97021484375,"s":194.1630859375,"ld":185.572265625,"qdel":1.0},"cca_rate":null,"belief_bounds":{"min_c":11.583984375,"max_c":11.583984375,"min_b":11.615234375,"max_b":11.615234375,"min_if":11.61572265625,"max_if":11.61572265625},"metrics":{"loss":88.572265625,"neg_delivered":-91.9775390625,"qdel":0.0,"shrink_c":true,"shrink_b":true,"shrink_maxc_mul":true,"shrink_maxc_add":true,"shrink_minc_mul":false,"shrink_minc_add":false},"chosen_move":null,"chosen_value":null},"children":[]}]},{"data":{"observation":{"a":379.76708984375,"s":170.99609375,"ld":180.0,"qdel":1.0},"cca_rate":11.6015625,"belief_bounds":{"min_c":11.6015625,"max_c":11.6015625,"min_b":11.6015625,"max_b":120.0,"min_if":23.20947265625,"max_if":28.77099609375},"metrics":{"loss":84.0,"neg_delivered":-68.810546875,"qdel":0.0,"shrink_c":true,"shrink_b":false,"shrink_maxc_mul":true,"shrink_maxc_add":true,"shrink_minc_mul":false,"shrink_minc_add":false},"chosen_move":{"Network":{"ld":185.611328125,"s":194.1650390625,"qdel":0.0}},"chosen_value":{"Value":{"belief_bounds":{"min_c":11.5849609375,"max_c":11.5849609375,"min_b":11.537109375,"max_b":11.537109375,"min_if":11.53857421875,"max_if":11.59228515625},"metrics":{"loss":88.611328125,"neg_delivered":-91.9794921875,"qdel":0.0,"shrink_c":true,"shrink_b":true,"shrink_maxc_mul":true,"shrink_maxc_add":true,"shrink_minc_mul":false,"shrink_minc_add":false}}}},"children":[{"data":{"observation":{"a":391.36865234375,"s":194.1650390625,"ld":185.611328125,"qdel":0.0},"cca_rate":null,"belief_bounds":{"min_c":11.5849609375,"max_c":11.5849609375,"min_b":11.537109375,"max_b":11.537109375,"min_if":11.53857421875,"max_if":11.59228515625},"metrics":{"loss":88.611328125,"neg_delivered":-91.9794921875,"qdel":0.0,"shrink_c":true,"shrink_b":true,"shrink_maxc_mul":true,"shrink_maxc_add":true,"shrink_minc_mul":false,"shrink_minc_add":false},"chosen_move":null,"chosen_value":null},"children":[]}]}]}]}]}